<Spawns>
  <Points>
    <Name>tk</Name>
    <UniqueId>029bfa45-b38b-4e32-bd00-89ece5e7d8e9</UniqueId>
    <Map>Felucca</Map>
    <X>5356</X>
    <Y>1619</Y>
    <Width>10</Width>
    <Height>10</Height>
    <CentreX>5361</CentreX>
    <CentreY>1624</CentreY>
    <CentreZ>0</CentreZ>
    <Range>5</Range>
    <MaxCount>1</MaxCount>
    <MinDelay>5</MinDelay>
    <MaxDelay>10</MaxDelay>
    <DelayInSec>False</DelayInSec>
    <Duration>0</Duration>
    <DespawnTime>0</DespawnTime>
    <ProximityRange>-1</ProximityRange>
    <ProximityTriggerSound>500</ProximityTriggerSound>
    <TriggerProbability>1</TriggerProbability>
    <InContainer>False</InContainer>
    <MinRefractory>0</MinRefractory>
    <MaxRefractory>0</MaxRefractory>
    <TODStart>0</TODStart>
    <TODEnd>0</TODEnd>
    <TODMode>0</TODMode>
    <KillReset>1</KillReset>
    <ExternalTriggering>False</ExternalTriggering>
    <SequentialSpawning>-1</SequentialSpawning>
    <AllowGhostTriggering>False</AllowGhostTriggering>
    <AllowNPCTriggering>False</AllowNPCTriggering>
    <SpawnOnTrigger>False</SpawnOnTrigger>
    <SmartSpawning>False</SmartSpawning>
    <TickReset>False</TickReset>
    <Team>0</Team>
    <Amount>1</Amount>
    <IsGroup>False</IsGroup>
    <IsRunning>True</IsRunning>
    <IsHomeRangeRelative>True</IsHomeRangeRelative>
    <Objects2>terathandrone:MX=1:SB=0:RT=0:TO=0:KL=0:RK=0:CA=1:DN=-1:DX=-1:SP=1:PR=-1</Objects2>
  </Points>
  <Points>
    <Name>tk</Name>
    <UniqueId>03d81b1c-b8fe-40ff-8562-b2452aad36c1</UniqueId>
    <Map>Felucca</Map>
    <X>5284</X>
    <Y>1716</Y>
    <Width>10</Width>
    <Height>10</Height>
    <CentreX>5289</CentreX>
    <CentreY>1721</CentreY>
    <CentreZ>-15</CentreZ>
    <Range>20</Range>
    <MaxCount>1</MaxCount>
    <MinDelay>5</MinDelay>
    <MaxDelay>10</MaxDelay>
    <DelayInSec>False</DelayInSec>
    <Duration>0</Duration>
    <DespawnTime>0</DespawnTime>
    <ProximityRange>-1</ProximityRange>
    <ProximityTriggerSound>500</ProximityTriggerSound>
    <TriggerProbability>1</TriggerProbability>
    <InContainer>False</InContainer>
    <MinRefractory>0</MinRefractory>
    <MaxRefractory>0</MaxRefractory>
    <TODStart>0</TODStart>
    <TODEnd>0</TODEnd>
    <TODMode>0</TODMode>
    <KillReset>1</KillReset>
    <ExternalTriggering>False</ExternalTriggering>
    <SequentialSpawning>-1</SequentialSpawning>
    <AllowGhostTriggering>False</AllowGhostTriggering>
    <AllowNPCTriggering>False</AllowNPCTriggering>
    <SpawnOnTrigger>False</SpawnOnTrigger>
    <SmartSpawning>False</SmartSpawning>
    <TickReset>False</TickReset>
    <Team>0</Team>
    <Amount>1</Amount>
    <IsGroup>False</IsGroup>
    <IsRunning>True</IsRunning>
    <IsHomeRangeRelative>True</IsHomeRangeRelative>
    <Objects2>ophidianmage:MX=1:SB=0:RT=0:TO=0:KL=0:RK=0:CA=1:DN=-1:DX=-1:SP=1:PR=-1</Objects2>
  </Points>
  <Points>
    <Name>tk</Name>
    <UniqueId>0665c20e-7bbc-4175-a0a8-d16f869b8805</UniqueId>
    <Map>Felucca</Map>
    <X>5361</X>
    <Y>1598</Y>
    <Width>2</Width>
    <Height>2</Height>
    <CentreX>5362</CentreX>
    <CentreY>1599</CentreY>
    <CentreZ>20</CentreZ>
    <Range>5</Range>
    <MaxCount>2</MaxCount>
    <MinDelay>5</MinDelay>
    <MaxDelay>10</MaxDelay>
    <DelayInSec>False</DelayInSec>
    <Duration>0</Duration>
    <DespawnTime>0</DespawnTime>
    <ProximityRange>-1</ProximityRange>
    <ProximityTriggerSound>500</ProximityTriggerSound>
    <TriggerProbability>1</TriggerProbability>
    <InContainer>False</InContainer>
    <MinRefractory>0</MinRefractory>
    <MaxRefractory>0</MaxRefractory>
    <TODStart>0</TODStart>
    <TODEnd>0</TODEnd>
    <TODMode>0</TODMode>
    <KillReset>1</KillReset>
    <ExternalTriggering>False</ExternalTriggering>
    <SequentialSpawning>-1</SequentialSpawning>
    <AllowGhostTriggering>False</AllowGhostTriggering>
    <AllowNPCTriggering>False</AllowNPCTriggering>
    <SpawnOnTrigger>False</SpawnOnTrigger>
    <SmartSpawning>False</SmartSpawning>
    <TickReset>False</TickReset>
    <Team>0</Team>
    <Amount>1</Amount>
    <IsGroup>False</IsGroup>
    <IsRunning>True</IsRunning>
    <IsHomeRangeRelative>True</IsHomeRangeRelative>
    <Objects2>ophidianwarrior:MX=1:SB=0:RT=0:TO=0:KL=0:RK=0:CA=1:DN=-1:DX=-1:SP=1:PR=-1:OBJ=ophidianmatriarch:MX=1:SB=0:RT=0:TO=0:KL=0:RK=0:CA=1:DN=-1:DX=-1:SP=1:PR=-1</Objects2>
  </Points>
  <Points>
    <Name>tk</Name>
    <UniqueId>068dea2e-5281-4617-8725-9407687e11fe</UniqueId>
    <Map>Felucca</Map>
    <X>5284</X>
    <Y>1569</Y>
    <Width>10</Width>
    <Height>10</Height>
    <CentreX>5289</CentreX>
    <CentreY>1574</CentreY>
    <CentreZ>0</CentreZ>
    <Range>5</Range>
    <MaxCount>1</MaxCount>
    <MinDelay>5</MinDelay>
    <MaxDelay>10</MaxDelay>
    <DelayInSec>False</DelayInSec>
    <Duration>0</Duration>
    <DespawnTime>0</DespawnTime>
    <ProximityRange>-1</ProximityRange>
    <ProximityTriggerSound>500</ProximityTriggerSound>
    <TriggerProbability>1</TriggerProbability>
    <InContainer>False</InContainer>
    <MinRefractory>0</MinRefractory>
    <MaxRefractory>0</MaxRefractory>
    <TODStart>0</TODStart>
    <TODEnd>0</TODEnd>
    <TODMode>0</TODMode>
    <KillReset>1</KillReset>
    <ExternalTriggering>False</ExternalTriggering>
    <SequentialSpawning>-1</SequentialSpawning>
    <AllowGhostTriggering>False</AllowGhostTriggering>
    <AllowNPCTriggering>False</AllowNPCTriggering>
    <SpawnOnTrigger>False</SpawnOnTrigger>
    <SmartSpawning>False</SmartSpawning>
    <TickReset>False</TickReset>
    <Team>0</Team>
    <Amount>1</Amount>
    <IsGroup>False</IsGroup>
    <IsRunning>True</IsRunning>
    <IsHomeRangeRelative>True</IsHomeRangeRelative>
    <Objects2>giantspider:MX=1:SB=0:RT=0:TO=0:KL=0:RK=0:CA=1:DN=-1:DX=-1:SP=1:PR=-1</Objects2>
  </Points>
  <Points>
    <Name>tk</Name>
    <UniqueId>0cec698a-0d5e-4d77-85a4-58f04aa97f3a</UniqueId>
    <Map>Felucca</Map>
    <X>5334</X>
    <Y>1612</Y>
    <Width>20</Width>
    <Height>20</Height>
    <CentreX>5344</CentreX>
    <CentreY>1622</CentreY>
    <CentreZ>0</CentreZ>
    <Range>10</Range>
    <MaxCount>3</MaxCount>
    <MinDelay>5</MinDelay>
    <MaxDelay>10</MaxDelay>
    <DelayInSec>False</DelayInSec>
    <Duration>0</Duration>
    <DespawnTime>0</DespawnTime>
    <ProximityRange>-1</ProximityRange>
    <ProximityTriggerSound>500</ProximityTriggerSound>
    <TriggerProbability>1</TriggerProbability>
    <InContainer>False</InContainer>
    <MinRefractory>0</MinRefractory>
    <MaxRefractory>0</MaxRefractory>
    <TODStart>0</TODStart>
    <TODEnd>0</TODEnd>
    <TODMode>0</TODMode>
    <KillReset>1</KillReset>
    <ExternalTriggering>False</ExternalTriggering>
    <SequentialSpawning>-1</SequentialSpawning>
    <AllowGhostTriggering>False</AllowGhostTriggering>
    <AllowNPCTriggering>False</AllowNPCTriggering>
    <SpawnOnTrigger>False</SpawnOnTrigger>
    <SmartSpawning>False</SmartSpawning>
    <TickReset>False</TickReset>
    <Team>0</Team>
    <Amount>1</Amount>
    <IsGroup>False</IsGroup>
    <IsRunning>True</IsRunning>
    <IsHomeRangeRelative>True</IsHomeRangeRelative>
    <Objects2>ophidianknight:MX=3:SB=0:RT=0:TO=0:KL=0:RK=0:CA=1:DN=-1:DX=-1:SP=1:PR=-1</Objects2>
  </Points>
  <Points>
    <Name>tk</Name>
    <UniqueId>10f60413-ad8b-4369-be70-96f6297270d6</UniqueId>
    <Map>Felucca</Map>
    <X>5345</X>
    <Y>1749</Y>
    <Width>10</Width>
    <Height>10</Height>
    <CentreX>5350</CentreX>
    <CentreY>1754</CentreY>
    <CentreZ>-125</CentreZ>
    <Range>15</Range>
    <MaxCount>3</MaxCount>
    <MinDelay>5</MinDelay>
    <MaxDelay>10</MaxDelay>
    <DelayInSec>False</DelayInSec>
    <Duration>0</Duration>
    <DespawnTime>0</DespawnTime>
    <ProximityRange>-1</ProximityRange>
    <ProximityTriggerSound>500</ProximityTriggerSound>
    <TriggerProbability>1</TriggerProbability>
    <InContainer>False</InContainer>
    <MinRefractory>0</MinRefractory>
    <MaxRefractory>0</MaxRefractory>
    <TODStart>0</TODStart>
    <TODEnd>0</TODEnd>
    <TODMode>0</TODMode>
    <KillReset>1</KillReset>
    <ExternalTriggering>False</ExternalTriggering>
    <SequentialSpawning>-1</SequentialSpawning>
    <AllowGhostTriggering>False</AllowGhostTriggering>
    <AllowNPCTriggering>False</AllowNPCTriggering>
    <SpawnOnTrigger>False</SpawnOnTrigger>
    <SmartSpawning>False</SmartSpawning>
    <TickReset>False</TickReset>
    <Team>0</Team>
    <Amount>1</Amount>
    <IsGroup>False</IsGroup>
    <IsRunning>True</IsRunning>
    <IsHomeRangeRelative>True</IsHomeRangeRelative>
    <Objects2>ophidianmage:MX=3:SB=0:RT=0:TO=0:KL=0:RK=0:CA=1:DN=-1:DX=-1:SP=1:PR=-1</Objects2>
  </Points>
  <Points>
    <Name>tk</Name>
    <UniqueId>1846546f-0709-4e5d-b2a3-713d23b3a238</UniqueId>
    <Map>Felucca</Map>
    <X>5285</X>
    <Y>1707</Y>
    <Width>10</Width>
    <Height>10</Height>
    <CentreX>5290</CentreX>
    <CentreY>1712</CentreY>
    <CentreZ>-13</CentreZ>
    <Range>25</Range>
    <MaxCount>1</MaxCount>
    <MinDelay>5</MinDelay>
    <MaxDelay>10</MaxDelay>
    <DelayInSec>False</DelayInSec>
    <Duration>0</Duration>
    <DespawnTime>0</DespawnTime>
    <ProximityRange>-1</ProximityRange>
    <ProximityTriggerSound>500</ProximityTriggerSound>
    <TriggerProbability>1</TriggerProbability>
    <InContainer>False</InContainer>
    <MinRefractory>0</MinRefractory>
    <MaxRefractory>0</MaxRefractory>
    <TODStart>0</TODStart>
    <TODEnd>0</TODEnd>
    <TODMode>0</TODMode>
    <KillReset>1</KillReset>
    <ExternalTriggering>False</ExternalTriggering>
    <SequentialSpawning>-1</SequentialSpawning>
    <AllowGhostTriggering>False</AllowGhostTriggering>
    <AllowNPCTriggering>False</AllowNPCTriggering>
    <SpawnOnTrigger>False</SpawnOnTrigger>
    <SmartSpawning>False</SmartSpawning>
    <TickReset>False</TickReset>
    <Team>0</Team>
    <Amount>1</Amount>
    <IsGroup>False</IsGroup>
    <IsRunning>True</IsRunning>
    <IsHomeRangeRelative>True</IsHomeRangeRelative>
    <Objects2>ophidianarchmage:MX=1:SB=0:RT=0:TO=0:KL=0:RK=0:CA=1:DN=-1:DX=-1:SP=1:PR=-1</Objects2>
  </Points>
  <Points>
    <Name>tk</Name>
    <UniqueId>1ac7d3e9-0b93-4c17-9eca-b962b7ee9113</UniqueId>
    <Map>Felucca</Map>
    <X>5150</X>
    <Y>1702</Y>
    <Width>10</Width>
    <Height>10</Height>
    <CentreX>5155</CentreX>
    <CentreY>1707</CentreY>
    <CentreZ>-35</CentreZ>
    <Range>10</Range>
    <MaxCount>9</MaxCount>
    <MinDelay>5</MinDelay>
    <MaxDelay>10</MaxDelay>
    <DelayInSec>False</DelayInSec>
    <Duration>0</Duration>
    <DespawnTime>0</DespawnTime>
    <ProximityRange>-1</ProximityRange>
    <ProximityTriggerSound>500</ProximityTriggerSound>
    <TriggerProbability>1</TriggerProbability>
    <InContainer>False</InContainer>
    <MinRefractory>0</MinRefractory>
    <MaxRefractory>0</MaxRefractory>
    <TODStart>0</TODStart>
    <TODEnd>0</TODEnd>
    <TODMode>0</TODMode>
    <KillReset>1</KillReset>
    <ExternalTriggering>False</ExternalTriggering>
    <SequentialSpawning>-1</SequentialSpawning>
    <AllowGhostTriggering>False</AllowGhostTriggering>
    <AllowNPCTriggering>False</AllowNPCTriggering>
    <SpawnOnTrigger>False</SpawnOnTrigger>
    <SmartSpawning>False</SmartSpawning>
    <TickReset>False</TickReset>
    <Team>0</Team>
    <Amount>1</Amount>
    <IsGroup>False</IsGroup>
    <IsRunning>True</IsRunning>
    <IsHomeRangeRelative>True</IsHomeRangeRelative>
    <Objects2>ophidianmage:MX=2:SB=0:RT=0:TO=0:KL=0:RK=0:CA=1:DN=-1:DX=-1:SP=1:PR=-1:OBJ=ophidianwarrior:MX=7:SB=0:RT=0:TO=0:KL=0:RK=0:CA=1:DN=-1:DX=-1:SP=1:PR=-1</Objects2>
  </Points>
  <Points>
    <Name>tk</Name>
    <UniqueId>1ee70958-b0af-4a38-a0ae-0270e508f8b0</UniqueId>
    <Map>Felucca</Map>
    <X>5323</X>
    <Y>1766</Y>
    <Width>10</Width>
    <Height>10</Height>
    <CentreX>5328</CentreX>
    <CentreY>1771</CentreY>
    <CentreZ>-120</CentreZ>
    <Range>5</Range>
    <MaxCount>1</MaxCount>
    <MinDelay>5</MinDelay>
    <MaxDelay>10</MaxDelay>
    <DelayInSec>False</DelayInSec>
    <Duration>0</Duration>
    <DespawnTime>0</DespawnTime>
    <ProximityRange>-1</ProximityRange>
    <ProximityTriggerSound>500</ProximityTriggerSound>
    <TriggerProbability>1</TriggerProbability>
    <InContainer>False</InContainer>
    <MinRefractory>0</MinRefractory>
    <MaxRefractory>0</MaxRefractory>
    <TODStart>0</TODStart>
    <TODEnd>0</TODEnd>
    <TODMode>0</TODMode>
    <KillReset>1</KillReset>
    <ExternalTriggering>False</ExternalTriggering>
    <SequentialSpawning>-1</SequentialSpawning>
    <AllowGhostTriggering>False</AllowGhostTriggering>
    <AllowNPCTriggering>False</AllowNPCTriggering>
    <SpawnOnTrigger>False</SpawnOnTrigger>
    <SmartSpawning>False</SmartSpawning>
    <TickReset>False</TickReset>
    <Team>0</Team>
    <Amount>1</Amount>
    <IsGroup>False</IsGroup>
    <IsRunning>True</IsRunning>
    <IsHomeRangeRelative>True</IsHomeRangeRelative>
    <Objects2>ophidianwarrior:MX=1:SB=0:RT=0:TO=0:KL=0:RK=0:CA=1:DN=-1:DX=-1:SP=1:PR=-1</Objects2>
  </Points>
  <Points>
    <Name>tk</Name>
    <UniqueId>21d4a256-269a-4b28-bd6e-048878009ab3</UniqueId>
    <Map>Felucca</Map>
    <X>5350</X>
    <Y>1587</Y>
    <Width>2</Width>
    <Height>2</Height>
    <CentreX>5351</CentreX>
    <CentreY>1588</CentreY>
    <CentreZ>0</CentreZ>
    <Range>15</Range>
    <MaxCount>1</MaxCount>
    <MinDelay>10</MinDelay>
    <MaxDelay>60</MaxDelay>
    <DelayInSec>True</DelayInSec>
    <Duration>0</Duration>
    <DespawnTime>0</DespawnTime>
    <ProximityRange>-1</ProximityRange>
    <ProximityTriggerSound>500</ProximityTriggerSound>
    <TriggerProbability>1</TriggerProbability>
    <InContainer>False</InContainer>
    <MinRefractory>0</MinRefractory>
    <MaxRefractory>0</MaxRefractory>
    <TODStart>0</TODStart>
    <TODEnd>0</TODEnd>
    <TODMode>0</TODMode>
    <KillReset>1</KillReset>
    <ExternalTriggering>False</ExternalTriggering>
    <SequentialSpawning>-1</SequentialSpawning>
    <AllowGhostTriggering>False</AllowGhostTriggering>
    <AllowNPCTriggering>False</AllowNPCTriggering>
    <SpawnOnTrigger>False</SpawnOnTrigger>
    <SmartSpawning>False</SmartSpawning>
    <TickReset>False</TickReset>
    <Team>0</Team>
    <Amount>1</Amount>
    <IsGroup>False</IsGroup>
    <IsRunning>True</IsRunning>
    <IsHomeRangeRelative>True</IsHomeRangeRelative>
    <Objects2>ophidianwarrior:MX=1:SB=0:RT=0:TO=0:KL=0:RK=0:CA=1:DN=-1:DX=-1:SP=1:PR=-1</Objects2>
  </Points>
  <Points>
    <Name>tk</Name>
    <UniqueId>23180b42-10de-4f8e-95e5-bcb1c595c2d0</UniqueId>
    <Map>Felucca</Map>
    <X>5308</X>
    <Y>1612</Y>
    <Width>10</Width>
    <Height>10</Height>
    <CentreX>5313</CentreX>
    <CentreY>1617</CentreY>
    <CentreZ>0</CentreZ>
    <Range>5</Range>
    <MaxCount>1</MaxCount>
    <MinDelay>5</MinDelay>
    <MaxDelay>10</MaxDelay>
    <DelayInSec>False</DelayInSec>
    <Duration>0</Duration>
    <DespawnTime>0</DespawnTime>
    <ProximityRange>-1</ProximityRange>
    <ProximityTriggerSound>500</ProximityTriggerSound>
    <TriggerProbability>1</TriggerProbability>
    <InContainer>False</InContainer>
    <MinRefractory>0</MinRefractory>
    <MaxRefractory>0</MaxRefractory>
    <TODStart>0</TODStart>
    <TODEnd>0</TODEnd>
    <TODMode>0</TODMode>
    <KillReset>1</KillReset>
    <ExternalTriggering>False</ExternalTriggering>
    <SequentialSpawning>-1</SequentialSpawning>
    <AllowGhostTriggering>False</AllowGhostTriggering>
    <AllowNPCTriggering>False</AllowNPCTriggering>
    <SpawnOnTrigger>False</SpawnOnTrigger>
    <SmartSpawning>False</SmartSpawning>
    <TickReset>False</TickReset>
    <Team>0</Team>
    <Amount>1</Amount>
    <IsGroup>False</IsGroup>
    <IsRunning>True</IsRunning>
    <IsHomeRangeRelative>True</IsHomeRangeRelative>
    <Objects2>ophidianmatriarch:MX=1:SB=0:RT=0:TO=0:KL=0:RK=0:CA=1:DN=-1:DX=-1:SP=1:PR=-1</Objects2>
  </Points>
  <Points>
    <Name>tk</Name>
    <UniqueId>24869f2f-fcd2-40a2-8d59-828db4339f6c</UniqueId>
    <Map>Felucca</Map>
    <X>5336</X>
    <Y>1541</Y>
    <Width>14</Width>
    <Height>14</Height>
    <CentreX>5343</CentreX>
    <CentreY>1548</CentreY>
    <CentreZ>0</CentreZ>
    <Range>7</Range>
    <MaxCount>4</MaxCount>
    <MinDelay>10</MinDelay>
    <MaxDelay>60</MaxDelay>
    <DelayInSec>True</DelayInSec>
    <Duration>0</Duration>
    <DespawnTime>0</DespawnTime>
    <ProximityRange>-1</ProximityRange>
    <ProximityTriggerSound>500</ProximityTriggerSound>
    <TriggerProbability>1</TriggerProbability>
    <InContainer>False</InContainer>
    <MinRefractory>0</MinRefractory>
    <MaxRefractory>0</MaxRefractory>
    <TODStart>0</TODStart>
    <TODEnd>0</TODEnd>
    <TODMode>0</TODMode>
    <KillReset>1</KillReset>
    <ExternalTriggering>False</ExternalTriggering>
    <SequentialSpawning>-1</SequentialSpawning>
    <AllowGhostTriggering>False</AllowGhostTriggering>
    <AllowNPCTriggering>False</AllowNPCTriggering>
    <SpawnOnTrigger>False</SpawnOnTrigger>
    <SmartSpawning>False</SmartSpawning>
    <TickReset>False</TickReset>
    <Team>0</Team>
    <Amount>1</Amount>
    <IsGroup>False</IsGroup>
    <IsRunning>True</IsRunning>
    <IsHomeRangeRelative>True</IsHomeRangeRelative>
    <Objects2>ophidianmage:MX=4:SB=0:RT=0:TO=0:KL=0:RK=0:CA=1:DN=-1:DX=-1:SP=1:PR=-1</Objects2>
  </Points>
  <Points>
    <Name>tk</Name>
    <UniqueId>25dff56e-46a5-4446-9d1a-6ab6abeb8005</UniqueId>
    <Map>Felucca</Map>
    <X>5356</X>
    <Y>1685</Y>
    <Width>10</Width>
    <Height>10</Height>
    <CentreX>5361</CentreX>
    <CentreY>1690</CentreY>
    <CentreZ>-51</CentreZ>
    <Range>5</Range>
    <MaxCount>1</MaxCount>
    <MinDelay>5</MinDelay>
    <MaxDelay>10</MaxDelay>
    <DelayInSec>False</DelayInSec>
    <Duration>0</Duration>
    <DespawnTime>0</DespawnTime>
    <ProximityRange>-1</ProximityRange>
    <ProximityTriggerSound>500</ProximityTriggerSound>
    <TriggerProbability>1</TriggerProbability>
    <InContainer>False</InContainer>
    <MinRefractory>0</MinRefractory>
    <MaxRefractory>0</MaxRefractory>
    <TODStart>0</TODStart>
    <TODEnd>0</TODEnd>
    <TODMode>0</TODMode>
    <KillReset>1</KillReset>
    <ExternalTriggering>False</ExternalTriggering>
    <SequentialSpawning>-1</SequentialSpawning>
    <AllowGhostTriggering>False</AllowGhostTriggering>
    <AllowNPCTriggering>False</AllowNPCTriggering>
    <SpawnOnTrigger>False</SpawnOnTrigger>
    <SmartSpawning>False</SmartSpawning>
    <TickReset>False</TickReset>
    <Team>0</Team>
    <Amount>1</Amount>
    <IsGroup>False</IsGroup>
    <IsRunning>True</IsRunning>
    <IsHomeRangeRelative>True</IsHomeRangeRelative>
    <Objects2>ophidianmage:MX=1:SB=0:RT=0:TO=0:KL=0:RK=0:CA=1:DN=-1:DX=-1:SP=1:PR=-1</Objects2>
  </Points>
  <Points>
    <Name>tk</Name>
    <UniqueId>286f4037-cdd4-40f9-849d-0e53cde34cc6</UniqueId>
    <Map>Felucca</Map>
    <X>5348</X>
    <Y>1560</Y>
    <Width>10</Width>
    <Height>10</Height>
    <CentreX>5353</CentreX>
    <CentreY>1565</CentreY>
    <CentreZ>0</CentreZ>
    <Range>5</Range>
    <MaxCount>4</MaxCount>
    <MinDelay>10</MinDelay>
    <MaxDelay>60</MaxDelay>
    <DelayInSec>True</DelayInSec>
    <Duration>0</Duration>
    <DespawnTime>0</DespawnTime>
    <ProximityRange>-1</ProximityRange>
    <ProximityTriggerSound>500</ProximityTriggerSound>
    <TriggerProbability>1</TriggerProbability>
    <InContainer>False</InContainer>
    <MinRefractory>0</MinRefractory>
    <MaxRefractory>0</MaxRefractory>
    <TODStart>0</TODStart>
    <TODEnd>0</TODEnd>
    <TODMode>0</TODMode>
    <KillReset>1</KillReset>
    <ExternalTriggering>False</ExternalTriggering>
    <SequentialSpawning>-1</SequentialSpawning>
    <AllowGhostTriggering>False</AllowGhostTriggering>
    <AllowNPCTriggering>False</AllowNPCTriggering>
    <SpawnOnTrigger>False</SpawnOnTrigger>
    <SmartSpawning>False</SmartSpawning>
    <TickReset>False</TickReset>
    <Team>0</Team>
    <Amount>1</Amount>
    <IsGroup>False</IsGroup>
    <IsRunning>True</IsRunning>
    <IsHomeRangeRelative>True</IsHomeRangeRelative>
    <Objects2>ophidianwarrior:MX=2:SB=0:RT=0:TO=0:KL=0:RK=0:CA=1:DN=-1:DX=-1:SP=1:PR=-1:OBJ=ophidianmage:MX=2:SB=0:RT=0:TO=0:KL=0:RK=0:CA=1:DN=-1:DX=-1:SP=1:PR=-1</Objects2>
  </Points>
  <Points>
    <Name>tk</Name>
    <UniqueId>2e37eed8-3720-4103-aff1-52b2b5086371</UniqueId>
    <Map>Felucca</Map>
    <X>5330</X>
    <Y>1621</Y>
    <Width>10</Width>
    <Height>10</Height>
    <CentreX>5335</CentreX>
    <CentreY>1626</CentreY>
    <CentreZ>0</CentreZ>
    <Range>5</Range>
    <MaxCount>1</MaxCount>
    <MinDelay>5</MinDelay>
    <MaxDelay>10</MaxDelay>
    <DelayInSec>False</DelayInSec>
    <Duration>0</Duration>
    <DespawnTime>0</DespawnTime>
    <ProximityRange>-1</ProximityRange>
    <ProximityTriggerSound>500</ProximityTriggerSound>
    <TriggerProbability>1</TriggerProbability>
    <InContainer>False</InContainer>
    <MinRefractory>0</MinRefractory>
    <MaxRefractory>0</MaxRefractory>
    <TODStart>0</TODStart>
    <TODEnd>0</TODEnd>
    <TODMode>0</TODMode>
    <KillReset>1</KillReset>
    <ExternalTriggering>False</ExternalTriggering>
    <SequentialSpawning>-1</SequentialSpawning>
    <AllowGhostTriggering>False</AllowGhostTriggering>
    <AllowNPCTriggering>False</AllowNPCTriggering>
    <SpawnOnTrigger>False</SpawnOnTrigger>
    <SmartSpawning>False</SmartSpawning>
    <TickReset>False</TickReset>
    <Team>0</Team>
    <Amount>1</Amount>
    <IsGroup>False</IsGroup>
    <IsRunning>True</IsRunning>
    <IsHomeRangeRelative>True</IsHomeRangeRelative>
    <Objects2>terathanwarrior:MX=1:SB=0:RT=0:TO=0:KL=0:RK=0:CA=1:DN=-1:DX=-1:SP=1:PR=-1</Objects2>
  </Points>
  <Points>
    <Name>tk</Name>
    <UniqueId>35241dce-96a4-4be1-8880-02a00e2c8025</UniqueId>
    <Map>Felucca</Map>
    <X>5324</X>
    <Y>1725</Y>
    <Width>30</Width>
    <Height>30</Height>
    <CentreX>5339</CentreX>
    <CentreY>1740</CentreY>
    <CentreZ>-69</CentreZ>
    <Range>15</Range>
    <MaxCount>2</MaxCount>
    <MinDelay>5</MinDelay>
    <MaxDelay>10</MaxDelay>
    <DelayInSec>False</DelayInSec>
    <Duration>0</Duration>
    <DespawnTime>0</DespawnTime>
    <ProximityRange>-1</ProximityRange>
    <ProximityTriggerSound>500</ProximityTriggerSound>
    <TriggerProbability>1</TriggerProbability>
    <InContainer>False</InContainer>
    <MinRefractory>0</MinRefractory>
    <MaxRefractory>0</MaxRefractory>
    <TODStart>0</TODStart>
    <TODEnd>0</TODEnd>
    <TODMode>0</TODMode>
    <KillReset>1</KillReset>
    <ExternalTriggering>False</ExternalTriggering>
    <SequentialSpawning>-1</SequentialSpawning>
    <AllowGhostTriggering>False</AllowGhostTriggering>
    <AllowNPCTriggering>False</AllowNPCTriggering>
    <SpawnOnTrigger>False</SpawnOnTrigger>
    <SmartSpawning>False</SmartSpawning>
    <TickReset>False</TickReset>
    <Team>0</Team>
    <Amount>1</Amount>
    <IsGroup>False</IsGroup>
    <IsRunning>True</IsRunning>
    <IsHomeRangeRelative>True</IsHomeRangeRelative>
    <Objects2>dragon:MX=1:SB=0:RT=0:TO=0:KL=0:RK=0:CA=1:DN=-1:DX=-1:SP=1:PR=-1:OBJ=drake:MX=1:SB=0:RT=0:TO=0:KL=0:RK=0:CA=1:DN=-1:DX=-1:SP=1:PR=-1</Objects2>
  </Points>
  <Points>
    <Name>tk</Name>
    <UniqueId>3b53b77a-00c6-4379-a20a-dfc1eacfd4c9</UniqueId>
    <Map>Felucca</Map>
    <X>5259</X>
    <Y>1521</Y>
    <Width>80</Width>
    <Height>80</Height>
    <CentreX>5299</CentreX>
    <CentreY>1561</CentreY>
    <CentreZ>0</CentreZ>
    <Range>5</Range>
    <MaxCount>20</MaxCount>
    <MinDelay>5</MinDelay>
    <MaxDelay>10</MaxDelay>
    <DelayInSec>False</DelayInSec>
    <Duration>0</Duration>
    <DespawnTime>0</DespawnTime>
    <ProximityRange>-1</ProximityRange>
    <ProximityTriggerSound>500</ProximityTriggerSound>
    <TriggerProbability>1</TriggerProbability>
    <InContainer>False</InContainer>
    <MinRefractory>0</MinRefractory>
    <MaxRefractory>0</MaxRefractory>
    <TODStart>0</TODStart>
    <TODEnd>0</TODEnd>
    <TODMode>0</TODMode>
    <KillReset>1</KillReset>
    <ExternalTriggering>False</ExternalTriggering>
    <SequentialSpawning>-1</SequentialSpawning>
    <AllowGhostTriggering>False</AllowGhostTriggering>
    <AllowNPCTriggering>False</AllowNPCTriggering>
    <SpawnOnTrigger>False</SpawnOnTrigger>
    <SmartSpawning>False</SmartSpawning>
    <TickReset>False</TickReset>
    <Team>0</Team>
    <Amount>1</Amount>
    <IsGroup>False</IsGroup>
    <IsRunning>True</IsRunning>
    <IsHomeRangeRelative>True</IsHomeRangeRelative>
    <Objects2>spiderssilk:MX=20:SB=0:RT=0:TO=0:KL=0:RK=0:CA=1:DN=-1:DX=-1:SP=1:PR=-1</Objects2>
  </Points>
  <Points>
    <Name>tk</Name>
    <UniqueId>4014e755-1a5a-49e2-9cae-105c8a6f1f76</UniqueId>
    <Map>Felucca</Map>
    <X>5297</X>
    <Y>1561</Y>
    <Width>2</Width>
    <Height>2</Height>
    <CentreX>5298</CentreX>
    <CentreY>1562</CentreY>
    <CentreZ>0</CentreZ>
    <Range>20</Range>
    <MaxCount>1</MaxCount>
    <MinDelay>5</MinDelay>
    <MaxDelay>10</MaxDelay>
    <DelayInSec>False</DelayInSec>
    <Duration>0</Duration>
    <DespawnTime>0</DespawnTime>
    <ProximityRange>-1</ProximityRange>
    <ProximityTriggerSound>500</ProximityTriggerSound>
    <TriggerProbability>1</TriggerProbability>
    <InContainer>False</InContainer>
    <MinRefractory>0</MinRefractory>
    <MaxRefractory>0</MaxRefractory>
    <TODStart>0</TODStart>
    <TODEnd>0</TODEnd>
    <TODMode>0</TODMode>
    <KillReset>1</KillReset>
    <ExternalTriggering>False</ExternalTriggering>
    <SequentialSpawning>-1</SequentialSpawning>
    <AllowGhostTriggering>False</AllowGhostTriggering>
    <AllowNPCTriggering>False</AllowNPCTriggering>
    <SpawnOnTrigger>False</SpawnOnTrigger>
    <SmartSpawning>False</SmartSpawning>
    <TickReset>False</TickReset>
    <Team>0</Team>
    <Amount>1</Amount>
    <IsGroup>False</IsGroup>
    <IsRunning>True</IsRunning>
    <IsHomeRangeRelative>True</IsHomeRangeRelative>
    <Objects2>giantspider:MX=1:SB=0:RT=0:TO=0:KL=0:RK=0:CA=1:DN=-1:DX=-1:SP=1:PR=-1</Objects2>
  </Points>
  <Points>
    <Name>tk</Name>
    <UniqueId>44414e49-5ee8-4b0b-b4c1-49f54ce1dd77</UniqueId>
    <Map>Felucca</Map>
    <X>5343</X>
    <Y>1638</Y>
    <Width>10</Width>
    <Height>10</Height>
    <CentreX>5348</CentreX>
    <CentreY>1643</CentreY>
    <CentreZ>0</CentreZ>
    <Range>5</Range>
    <MaxCount>1</MaxCount>
    <MinDelay>5</MinDelay>
    <MaxDelay>10</MaxDelay>
    <DelayInSec>False</DelayInSec>
    <Duration>0</Duration>
    <DespawnTime>0</DespawnTime>
    <ProximityRange>-1</ProximityRange>
    <ProximityTriggerSound>500</ProximityTriggerSound>
    <TriggerProbability>1</TriggerProbability>
    <InContainer>False</InContainer>
    <MinRefractory>0</MinRefractory>
    <MaxRefractory>0</MaxRefractory>
    <TODStart>0</TODStart>
    <TODEnd>0</TODEnd>
    <TODMode>0</TODMode>
    <KillReset>1</KillReset>
    <ExternalTriggering>False</ExternalTriggering>
    <SequentialSpawning>-1</SequentialSpawning>
    <AllowGhostTriggering>False</AllowGhostTriggering>
    <AllowNPCTriggering>False</AllowNPCTriggering>
    <SpawnOnTrigger>False</SpawnOnTrigger>
    <SmartSpawning>False</SmartSpawning>
    <TickReset>False</TickReset>
    <Team>0</Team>
    <Amount>1</Amount>
    <IsGroup>False</IsGroup>
    <IsRunning>True</IsRunning>
    <IsHomeRangeRelative>True</IsHomeRangeRelative>
    <Objects2>ophidianknight:MX=1:SB=0:RT=0:TO=0:KL=0:RK=0:CA=1:DN=-1:DX=-1:SP=1:PR=-1</Objects2>
  </Points>
  <Points>
    <Name>tk</Name>
    <UniqueId>46360639-7e3c-4d22-9f41-dce0333e3559</UniqueId>
    <Map>Felucca</Map>
    <X>5340</X>
    <Y>1762</Y>
    <Width>16</Width>
    <Height>16</Height>
    <CentreX>5348</CentreX>
    <CentreY>1770</CentreY>
    <CentreZ>-119</CentreZ>
    <Range>8</Range>
    <MaxCount>3</MaxCount>
    <MinDelay>5</MinDelay>
    <MaxDelay>10</MaxDelay>
    <DelayInSec>False</DelayInSec>
    <Duration>0</Duration>
    <DespawnTime>0</DespawnTime>
    <ProximityRange>-1</ProximityRange>
    <ProximityTriggerSound>500</ProximityTriggerSound>
    <TriggerProbability>1</TriggerProbability>
    <InContainer>False</InContainer>
    <MinRefractory>0</MinRefractory>
    <MaxRefractory>0</MaxRefractory>
    <TODStart>0</TODStart>
    <TODEnd>0</TODEnd>
    <TODMode>0</TODMode>
    <KillReset>1</KillReset>
    <ExternalTriggering>False</ExternalTriggering>
    <SequentialSpawning>-1</SequentialSpawning>
    <AllowGhostTriggering>False</AllowGhostTriggering>
    <AllowNPCTriggering>False</AllowNPCTriggering>
    <SpawnOnTrigger>False</SpawnOnTrigger>
    <SmartSpawning>False</SmartSpawning>
    <TickReset>False</TickReset>
    <Team>0</Team>
    <Amount>1</Amount>
    <IsGroup>False</IsGroup>
    <IsRunning>True</IsRunning>
    <IsHomeRangeRelative>True</IsHomeRangeRelative>
    <Objects2>ophidianwarrior:MX=3:SB=0:RT=0:TO=0:KL=0:RK=0:CA=1:DN=-1:DX=-1:SP=1:PR=-1</Objects2>
  </Points>
  <Points>
    <Name>tk</Name>
    <UniqueId>47ba1578-64bc-4725-ace7-039773090e14</UniqueId>
    <Map>Felucca</Map>
    <X>5315</X>
    <Y>1584</Y>
    <Width>10</Width>
    <Height>10</Height>
    <CentreX>5320</CentreX>
    <CentreY>1589</CentreY>
    <CentreZ>0</CentreZ>
    <Range>5</Range>
    <MaxCount>1</MaxCount>
    <MinDelay>10</MinDelay>
    <MaxDelay>60</MaxDelay>
    <DelayInSec>True</DelayInSec>
    <Duration>0</Duration>
    <DespawnTime>0</DespawnTime>
    <ProximityRange>-1</ProximityRange>
    <ProximityTriggerSound>500</ProximityTriggerSound>
    <TriggerProbability>1</TriggerProbability>
    <InContainer>False</InContainer>
    <MinRefractory>0</MinRefractory>
    <MaxRefractory>0</MaxRefractory>
    <TODStart>0</TODStart>
    <TODEnd>0</TODEnd>
    <TODMode>0</TODMode>
    <KillReset>1</KillReset>
    <ExternalTriggering>False</ExternalTriggering>
    <SequentialSpawning>-1</SequentialSpawning>
    <AllowGhostTriggering>False</AllowGhostTriggering>
    <AllowNPCTriggering>False</AllowNPCTriggering>
    <SpawnOnTrigger>False</SpawnOnTrigger>
    <SmartSpawning>False</SmartSpawning>
    <TickReset>False</TickReset>
    <Team>0</Team>
    <Amount>1</Amount>
    <IsGroup>False</IsGroup>
    <IsRunning>True</IsRunning>
    <IsHomeRangeRelative>True</IsHomeRangeRelative>
    <Objects2>terathanavenger:MX=1:SB=0:RT=0:TO=0:KL=0:RK=0:CA=1:DN=-1:DX=-1:SP=1:PR=-1</Objects2>
  </Points>
  <Points>
    <Name>tk</Name>
    <UniqueId>49ada250-3875-41d2-9ae3-975ab213dce1</UniqueId>
    <Map>Felucca</Map>
    <X>5323</X>
    <Y>1600</Y>
    <Width>20</Width>
    <Height>20</Height>
    <CentreX>5333</CentreX>
    <CentreY>1610</CentreY>
    <CentreZ>0</CentreZ>
    <Range>10</Range>
    <MaxCount>2</MaxCount>
    <MinDelay>5</MinDelay>
    <MaxDelay>10</MaxDelay>
    <DelayInSec>False</DelayInSec>
    <Duration>0</Duration>
    <DespawnTime>0</DespawnTime>
    <ProximityRange>-1</ProximityRange>
    <ProximityTriggerSound>500</ProximityTriggerSound>
    <TriggerProbability>1</TriggerProbability>
    <InContainer>False</InContainer>
    <MinRefractory>0</MinRefractory>
    <MaxRefractory>0</MaxRefractory>
    <TODStart>0</TODStart>
    <TODEnd>0</TODEnd>
    <TODMode>0</TODMode>
    <KillReset>1</KillReset>
    <ExternalTriggering>False</ExternalTriggering>
    <SequentialSpawning>-1</SequentialSpawning>
    <AllowGhostTriggering>False</AllowGhostTriggering>
    <AllowNPCTriggering>False</AllowNPCTriggering>
    <SpawnOnTrigger>False</SpawnOnTrigger>
    <SmartSpawning>False</SmartSpawning>
    <TickReset>False</TickReset>
    <Team>0</Team>
    <Amount>1</Amount>
    <IsGroup>False</IsGroup>
    <IsRunning>True</IsRunning>
    <IsHomeRangeRelative>True</IsHomeRangeRelative>
    <Objects2>ophidianknight:MX=1:SB=0:RT=0:TO=0:KL=0:RK=0:CA=1:DN=-1:DX=-1:SP=1:PR=-1:OBJ=ophidianmatriarch:MX=1:SB=0:RT=0:TO=0:KL=0:RK=0:CA=1:DN=-1:DX=-1:SP=1:PR=-1</Objects2>
  </Points>
  <Points>
    <Name>tk</Name>
    <UniqueId>5da11a2c-3b72-44aa-83f8-500e13ea3958</UniqueId>
    <Map>Felucca</Map>
    <X>5330</X>
    <Y>1552</Y>
    <Width>10</Width>
    <Height>10</Height>
    <CentreX>5335</CentreX>
    <CentreY>1557</CentreY>
    <CentreZ>0</CentreZ>
    <Range>5</Range>
    <MaxCount>3</MaxCount>
    <MinDelay>10</MinDelay>
    <MaxDelay>60</MaxDelay>
    <DelayInSec>True</DelayInSec>
    <Duration>0</Duration>
    <DespawnTime>0</DespawnTime>
    <ProximityRange>-1</ProximityRange>
    <ProximityTriggerSound>500</ProximityTriggerSound>
    <TriggerProbability>1</TriggerProbability>
    <InContainer>False</InContainer>
    <MinRefractory>0</MinRefractory>
    <MaxRefractory>0</MaxRefractory>
    <TODStart>0</TODStart>
    <TODEnd>0</TODEnd>
    <TODMode>0</TODMode>
    <KillReset>1</KillReset>
    <ExternalTriggering>False</ExternalTriggering>
    <SequentialSpawning>-1</SequentialSpawning>
    <AllowGhostTriggering>False</AllowGhostTriggering>
    <AllowNPCTriggering>False</AllowNPCTriggering>
    <SpawnOnTrigger>False</SpawnOnTrigger>
    <SmartSpawning>False</SmartSpawning>
    <TickReset>False</TickReset>
    <Team>0</Team>
    <Amount>1</Amount>
    <IsGroup>False</IsGroup>
    <IsRunning>True</IsRunning>
    <IsHomeRangeRelative>True</IsHomeRangeRelative>
    <Objects2>ophidianwarrior:MX=3:SB=0:RT=0:TO=0:KL=0:RK=0:CA=1:DN=-1:DX=-1:SP=1:PR=-1</Objects2>
  </Points>
  <Points>
    <Name>tk</Name>
    <UniqueId>60859252-f444-428c-a0ae-40939879163c</UniqueId>
    <Map>Felucca</Map>
    <X>5189</X>
    <Y>1643</Y>
    <Width>50</Width>
    <Height>50</Height>
    <CentreX>5214</CentreX>
    <CentreY>1668</CentreY>
    <CentreZ>0</CentreZ>
    <Range>35</Range>
    <MaxCount>6</MaxCount>
    <MinDelay>5</MinDelay>
    <MaxDelay>10</MaxDelay>
    <DelayInSec>False</DelayInSec>
    <Duration>0</Duration>
    <DespawnTime>0</DespawnTime>
    <ProximityRange>-1</ProximityRange>
    <ProximityTriggerSound>500</ProximityTriggerSound>
    <TriggerProbability>1</TriggerProbability>
    <InContainer>False</InContainer>
    <MinRefractory>0</MinRefractory>
    <MaxRefractory>0</MaxRefractory>
    <TODStart>0</TODStart>
    <TODEnd>0</TODEnd>
    <TODMode>0</TODMode>
    <KillReset>1</KillReset>
    <ExternalTriggering>False</ExternalTriggering>
    <SequentialSpawning>-1</SequentialSpawning>
    <AllowGhostTriggering>False</AllowGhostTriggering>
    <AllowNPCTriggering>False</AllowNPCTriggering>
    <SpawnOnTrigger>False</SpawnOnTrigger>
    <SmartSpawning>False</SmartSpawning>
    <TickReset>False</TickReset>
    <Team>0</Team>
    <Amount>1</Amount>
    <IsGroup>False</IsGroup>
    <IsRunning>True</IsRunning>
    <IsHomeRangeRelative>True</IsHomeRangeRelative>
    <Objects2>ophidianwarrior:MX=2:SB=0:RT=0:TO=0:KL=0:RK=0:CA=1:DN=-1:DX=-1:SP=1:PR=-1:OBJ=ophidianmage:MX=4:SB=0:RT=0:TO=0:KL=0:RK=0:CA=1:DN=-1:DX=-1:SP=1:PR=-1</Objects2>
  </Points>
  <Points>
    <Name>tk</Name>
    <UniqueId>633cbfea-7511-4dfe-a2b1-1681bf8ccaf8</UniqueId>
    <Map>Felucca</Map>
    <X>5339</X>
    <Y>1652</Y>
    <Width>10</Width>
    <Height>10</Height>
    <CentreX>5344</CentreX>
    <CentreY>1657</CentreY>
    <CentreZ>-5</CentreZ>
    <Range>5</Range>
    <MaxCount>1</MaxCount>
    <MinDelay>5</MinDelay>
    <MaxDelay>10</MaxDelay>
    <DelayInSec>False</DelayInSec>
    <Duration>0</Duration>
    <DespawnTime>0</DespawnTime>
    <ProximityRange>-1</ProximityRange>
    <ProximityTriggerSound>500</ProximityTriggerSound>
    <TriggerProbability>1</TriggerProbability>
    <InContainer>False</InContainer>
    <MinRefractory>0</MinRefractory>
    <MaxRefractory>0</MaxRefractory>
    <TODStart>0</TODStart>
    <TODEnd>0</TODEnd>
    <TODMode>0</TODMode>
    <KillReset>1</KillReset>
    <ExternalTriggering>False</ExternalTriggering>
    <SequentialSpawning>-1</SequentialSpawning>
    <AllowGhostTriggering>False</AllowGhostTriggering>
    <AllowNPCTriggering>False</AllowNPCTriggering>
    <SpawnOnTrigger>False</SpawnOnTrigger>
    <SmartSpawning>False</SmartSpawning>
    <TickReset>False</TickReset>
    <Team>0</Team>
    <Amount>1</Amount>
    <IsGroup>False</IsGroup>
    <IsRunning>True</IsRunning>
    <IsHomeRangeRelative>True</IsHomeRangeRelative>
    <Objects2>ophidianknight:MX=1:SB=0:RT=0:TO=0:KL=0:RK=0:CA=1:DN=-1:DX=-1:SP=1:PR=-1</Objects2>
  </Points>
  <Points>
    <Name>tk</Name>
    <UniqueId>63824936-73ba-4576-841a-c996cc04e090</UniqueId>
    <Map>Felucca</Map>
    <X>5307</X>
    <Y>1585</Y>
    <Width>10</Width>
    <Height>10</Height>
    <CentreX>5312</CentreX>
    <CentreY>1590</CentreY>
    <CentreZ>0</CentreZ>
    <Range>5</Range>
    <MaxCount>1</MaxCount>
    <MinDelay>10</MinDelay>
    <MaxDelay>60</MaxDelay>
    <DelayInSec>True</DelayInSec>
    <Duration>0</Duration>
    <DespawnTime>0</DespawnTime>
    <ProximityRange>-1</ProximityRange>
    <ProximityTriggerSound>500</ProximityTriggerSound>
    <TriggerProbability>1</TriggerProbability>
    <InContainer>False</InContainer>
    <MinRefractory>0</MinRefractory>
    <MaxRefractory>0</MaxRefractory>
    <TODStart>0</TODStart>
    <TODEnd>0</TODEnd>
    <TODMode>0</TODMode>
    <KillReset>1</KillReset>
    <ExternalTriggering>False</ExternalTriggering>
    <SequentialSpawning>-1</SequentialSpawning>
    <AllowGhostTriggering>False</AllowGhostTriggering>
    <AllowNPCTriggering>False</AllowNPCTriggering>
    <SpawnOnTrigger>False</SpawnOnTrigger>
    <SmartSpawning>False</SmartSpawning>
    <TickReset>False</TickReset>
    <Team>0</Team>
    <Amount>1</Amount>
    <IsGroup>False</IsGroup>
    <IsRunning>True</IsRunning>
    <IsHomeRangeRelative>True</IsHomeRangeRelative>
    <Objects2>terathanwarrior:MX=1:SB=0:RT=0:TO=0:KL=0:RK=0:CA=1:DN=-1:DX=-1:SP=1:PR=-1</Objects2>
  </Points>
  <Points>
    <Name>tk</Name>
    <UniqueId>6628ff39-0577-40f8-8b7f-ff854bdf7752</UniqueId>
    <Map>Felucca</Map>
    <X>5345</X>
    <Y>1547</Y>
    <Width>10</Width>
    <Height>10</Height>
    <CentreX>5350</CentreX>
    <CentreY>1552</CentreY>
    <CentreZ>0</CentreZ>
    <Range>5</Range>
    <MaxCount>2</MaxCount>
    <MinDelay>10</MinDelay>
    <MaxDelay>60</MaxDelay>
    <DelayInSec>True</DelayInSec>
    <Duration>0</Duration>
    <DespawnTime>0</DespawnTime>
    <ProximityRange>-1</ProximityRange>
    <ProximityTriggerSound>500</ProximityTriggerSound>
    <TriggerProbability>1</TriggerProbability>
    <InContainer>False</InContainer>
    <MinRefractory>0</MinRefractory>
    <MaxRefractory>0</MaxRefractory>
    <TODStart>0</TODStart>
    <TODEnd>0</TODEnd>
    <TODMode>0</TODMode>
    <KillReset>1</KillReset>
    <ExternalTriggering>False</ExternalTriggering>
    <SequentialSpawning>-1</SequentialSpawning>
    <AllowGhostTriggering>False</AllowGhostTriggering>
    <AllowNPCTriggering>False</AllowNPCTriggering>
    <SpawnOnTrigger>False</SpawnOnTrigger>
    <SmartSpawning>False</SmartSpawning>
    <TickReset>False</TickReset>
    <Team>0</Team>
    <Amount>1</Amount>
    <IsGroup>False</IsGroup>
    <IsRunning>True</IsRunning>
    <IsHomeRangeRelative>True</IsHomeRangeRelative>
    <Objects2>ophidianwarrior:MX=2:SB=0:RT=0:TO=0:KL=0:RK=0:CA=1:DN=-1:DX=-1:SP=1:PR=-1</Objects2>
  </Points>
  <Points>
    <Name>tk</Name>
    <UniqueId>67bbb9d6-7493-43ad-ba75-ee8c66d3167e</UniqueId>
    <Map>Felucca</Map>
    <X>5343</X>
    <Y>1683</Y>
    <Width>10</Width>
    <Height>10</Height>
    <CentreX>5348</CentreX>
    <CentreY>1688</CentreY>
    <CentreZ>-51</CentreZ>
    <Range>5</Range>
    <MaxCount>1</MaxCount>
    <MinDelay>5</MinDelay>
    <MaxDelay>10</MaxDelay>
    <DelayInSec>False</DelayInSec>
    <Duration>0</Duration>
    <DespawnTime>0</DespawnTime>
    <ProximityRange>-1</ProximityRange>
    <ProximityTriggerSound>500</ProximityTriggerSound>
    <TriggerProbability>1</TriggerProbability>
    <InContainer>False</InContainer>
    <MinRefractory>0</MinRefractory>
    <MaxRefractory>0</MaxRefractory>
    <TODStart>0</TODStart>
    <TODEnd>0</TODEnd>
    <TODMode>0</TODMode>
    <KillReset>1</KillReset>
    <ExternalTriggering>False</ExternalTriggering>
    <SequentialSpawning>-1</SequentialSpawning>
    <AllowGhostTriggering>False</AllowGhostTriggering>
    <AllowNPCTriggering>False</AllowNPCTriggering>
    <SpawnOnTrigger>False</SpawnOnTrigger>
    <SmartSpawning>False</SmartSpawning>
    <TickReset>False</TickReset>
    <Team>0</Team>
    <Amount>1</Amount>
    <IsGroup>False</IsGroup>
    <IsRunning>True</IsRunning>
    <IsHomeRangeRelative>True</IsHomeRangeRelative>
    <Objects2>ophidianmage:MX=1:SB=0:RT=0:TO=0:KL=0:RK=0:CA=1:DN=-1:DX=-1:SP=1:PR=-1</Objects2>
  </Points>
  <Points>
    <Name>tk</Name>
    <UniqueId>6e6ad1ab-9c5b-4df4-b434-f50700f9644a</UniqueId>
    <Map>Felucca</Map>
    <X>5338</X>
    <Y>1544</Y>
    <Width>10</Width>
    <Height>10</Height>
    <CentreX>5343</CentreX>
    <CentreY>1549</CentreY>
    <CentreZ>0</CentreZ>
    <Range>8</Range>
    <MaxCount>3</MaxCount>
    <MinDelay>10</MinDelay>
    <MaxDelay>60</MaxDelay>
    <DelayInSec>True</DelayInSec>
    <Duration>0</Duration>
    <DespawnTime>0</DespawnTime>
    <ProximityRange>-1</ProximityRange>
    <ProximityTriggerSound>500</ProximityTriggerSound>
    <TriggerProbability>1</TriggerProbability>
    <InContainer>False</InContainer>
    <MinRefractory>0</MinRefractory>
    <MaxRefractory>0</MaxRefractory>
    <TODStart>0</TODStart>
    <TODEnd>0</TODEnd>
    <TODMode>0</TODMode>
    <KillReset>1</KillReset>
    <ExternalTriggering>False</ExternalTriggering>
    <SequentialSpawning>-1</SequentialSpawning>
    <AllowGhostTriggering>False</AllowGhostTriggering>
    <AllowNPCTriggering>False</AllowNPCTriggering>
    <SpawnOnTrigger>False</SpawnOnTrigger>
    <SmartSpawning>False</SmartSpawning>
    <TickReset>False</TickReset>
    <Team>0</Team>
    <Amount>1</Amount>
    <IsGroup>False</IsGroup>
    <IsRunning>True</IsRunning>
    <IsHomeRangeRelative>True</IsHomeRangeRelative>
    <Objects2>ophidianarchmage:MX=3:SB=0:RT=0:TO=0:KL=0:RK=0:CA=1:DN=-1:DX=-1:SP=1:PR=-1</Objects2>
  </Points>
  <Points>
    <Name>tk</Name>
    <UniqueId>71536c71-8c72-4335-a7a7-da004b8134dd</UniqueId>
    <Map>Felucca</Map>
    <X>5338</X>
    <Y>1532</Y>
    <Width>14</Width>
    <Height>14</Height>
    <CentreX>5345</CentreX>
    <CentreY>1539</CentreY>
    <CentreZ>0</CentreZ>
    <Range>7</Range>
    <MaxCount>4</MaxCount>
    <MinDelay>10</MinDelay>
    <MaxDelay>60</MaxDelay>
    <DelayInSec>True</DelayInSec>
    <Duration>0</Duration>
    <DespawnTime>0</DespawnTime>
    <ProximityRange>-1</ProximityRange>
    <ProximityTriggerSound>500</ProximityTriggerSound>
    <TriggerProbability>1</TriggerProbability>
    <InContainer>False</InContainer>
    <MinRefractory>0</MinRefractory>
    <MaxRefractory>0</MaxRefractory>
    <TODStart>0</TODStart>
    <TODEnd>0</TODEnd>
    <TODMode>0</TODMode>
    <KillReset>1</KillReset>
    <ExternalTriggering>False</ExternalTriggering>
    <SequentialSpawning>-1</SequentialSpawning>
    <AllowGhostTriggering>False</AllowGhostTriggering>
    <AllowNPCTriggering>False</AllowNPCTriggering>
    <SpawnOnTrigger>False</SpawnOnTrigger>
    <SmartSpawning>False</SmartSpawning>
    <TickReset>False</TickReset>
    <Team>0</Team>
    <Amount>1</Amount>
    <IsGroup>False</IsGroup>
    <IsRunning>True</IsRunning>
    <IsHomeRangeRelative>True</IsHomeRangeRelative>
    <Objects2>ophidianwarrior:MX=4:SB=0:RT=0:TO=0:KL=0:RK=0:CA=1:DN=-1:DX=-1:SP=1:PR=-1</Objects2>
  </Points>
  <Points>
    <Name>tk</Name>
    <UniqueId>71af7992-e820-42e4-bdb1-a262118e6e1a</UniqueId>
    <Map>Felucca</Map>
    <X>5295</X>
    <Y>1546</Y>
    <Width>10</Width>
    <Height>10</Height>
    <CentreX>5300</CentreX>
    <CentreY>1551</CentreY>
    <CentreZ>0</CentreZ>
    <Range>5</Range>
    <MaxCount>2</MaxCount>
    <MinDelay>5</MinDelay>
    <MaxDelay>10</MaxDelay>
    <DelayInSec>False</DelayInSec>
    <Duration>0</Duration>
    <DespawnTime>0</DespawnTime>
    <ProximityRange>-1</ProximityRange>
    <ProximityTriggerSound>500</ProximityTriggerSound>
    <TriggerProbability>1</TriggerProbability>
    <InContainer>False</InContainer>
    <MinRefractory>0</MinRefractory>
    <MaxRefractory>0</MaxRefractory>
    <TODStart>0</TODStart>
    <TODEnd>0</TODEnd>
    <TODMode>0</TODMode>
    <KillReset>1</KillReset>
    <ExternalTriggering>False</ExternalTriggering>
    <SequentialSpawning>-1</SequentialSpawning>
    <AllowGhostTriggering>False</AllowGhostTriggering>
    <AllowNPCTriggering>False</AllowNPCTriggering>
    <SpawnOnTrigger>False</SpawnOnTrigger>
    <SmartSpawning>False</SmartSpawning>
    <TickReset>False</TickReset>
    <Team>0</Team>
    <Amount>1</Amount>
    <IsGroup>False</IsGroup>
    <IsRunning>True</IsRunning>
    <IsHomeRangeRelative>True</IsHomeRangeRelative>
    <Objects2>giantspider:MX=2:SB=0:RT=0:TO=0:KL=0:RK=0:CA=1:DN=-1:DX=-1:SP=1:PR=-1</Objects2>
  </Points>
  <Points>
    <Name>tk</Name>
    <UniqueId>75895f63-ff53-43f4-bde6-b06a5d5375c2</UniqueId>
    <Map>Felucca</Map>
    <X>5327</X>
    <Y>1536</Y>
    <Width>10</Width>
    <Height>10</Height>
    <CentreX>5332</CentreX>
    <CentreY>1541</CentreY>
    <CentreZ>0</CentreZ>
    <Range>5</Range>
    <MaxCount>2</MaxCount>
    <MinDelay>10</MinDelay>
    <MaxDelay>60</MaxDelay>
    <DelayInSec>True</DelayInSec>
    <Duration>0</Duration>
    <DespawnTime>0</DespawnTime>
    <ProximityRange>-1</ProximityRange>
    <ProximityTriggerSound>500</ProximityTriggerSound>
    <TriggerProbability>1</TriggerProbability>
    <InContainer>False</InContainer>
    <MinRefractory>0</MinRefractory>
    <MaxRefractory>0</MaxRefractory>
    <TODStart>0</TODStart>
    <TODEnd>0</TODEnd>
    <TODMode>0</TODMode>
    <KillReset>1</KillReset>
    <ExternalTriggering>False</ExternalTriggering>
    <SequentialSpawning>-1</SequentialSpawning>
    <AllowGhostTriggering>False</AllowGhostTriggering>
    <AllowNPCTriggering>False</AllowNPCTriggering>
    <SpawnOnTrigger>False</SpawnOnTrigger>
    <SmartSpawning>False</SmartSpawning>
    <TickReset>False</TickReset>
    <Team>0</Team>
    <Amount>1</Amount>
    <IsGroup>False</IsGroup>
    <IsRunning>True</IsRunning>
    <IsHomeRangeRelative>True</IsHomeRangeRelative>
    <Objects2>ophidianmage:MX=2:SB=0:RT=0:TO=0:KL=0:RK=0:CA=1:DN=-1:DX=-1:SP=1:PR=-1</Objects2>
  </Points>
  <Points>
    <Name>tk</Name>
    <UniqueId>78a214c5-3153-4787-9b97-a52762a09d31</UniqueId>
    <Map>Felucca</Map>
    <X>5304</X>
    <Y>1680</Y>
    <Width>30</Width>
    <Height>30</Height>
    <CentreX>5319</CentreX>
    <CentreY>1695</CentreY>
    <CentreZ>-13</CentreZ>
    <Range>35</Range>
    <MaxCount>3</MaxCount>
    <MinDelay>5</MinDelay>
    <MaxDelay>10</MaxDelay>
    <DelayInSec>False</DelayInSec>
    <Duration>0</Duration>
    <DespawnTime>0</DespawnTime>
    <ProximityRange>-1</ProximityRange>
    <ProximityTriggerSound>500</ProximityTriggerSound>
    <TriggerProbability>1</TriggerProbability>
    <InContainer>False</InContainer>
    <MinRefractory>0</MinRefractory>
    <MaxRefractory>0</MaxRefractory>
    <TODStart>0</TODStart>
    <TODEnd>0</TODEnd>
    <TODMode>0</TODMode>
    <KillReset>1</KillReset>
    <ExternalTriggering>False</ExternalTriggering>
    <SequentialSpawning>-1</SequentialSpawning>
    <AllowGhostTriggering>False</AllowGhostTriggering>
    <AllowNPCTriggering>False</AllowNPCTriggering>
    <SpawnOnTrigger>False</SpawnOnTrigger>
    <SmartSpawning>False</SmartSpawning>
    <TickReset>False</TickReset>
    <Team>0</Team>
    <Amount>1</Amount>
    <IsGroup>False</IsGroup>
    <IsRunning>True</IsRunning>
    <IsHomeRangeRelative>True</IsHomeRangeRelative>
    <Objects2>ophidianmage:MX=3:SB=0:RT=0:TO=0:KL=0:RK=0:CA=1:DN=-1:DX=-1:SP=1:PR=-1</Objects2>
  </Points>
  <Points>
    <Name>tk</Name>
    <UniqueId>7dc37a9f-b894-46b7-b804-b03617856003</UniqueId>
    <Map>Felucca</Map>
    <X>5361</X>
    <Y>1747</Y>
    <Width>10</Width>
    <Height>10</Height>
    <CentreX>5366</CentreX>
    <CentreY>1752</CentreY>
    <CentreZ>-87</CentreZ>
    <Range>20</Range>
    <MaxCount>1</MaxCount>
    <MinDelay>5</MinDelay>
    <MaxDelay>10</MaxDelay>
    <DelayInSec>False</DelayInSec>
    <Duration>0</Duration>
    <DespawnTime>0</DespawnTime>
    <ProximityRange>-1</ProximityRange>
    <ProximityTriggerSound>500</ProximityTriggerSound>
    <TriggerProbability>1</TriggerProbability>
    <InContainer>False</InContainer>
    <MinRefractory>0</MinRefractory>
    <MaxRefractory>0</MaxRefractory>
    <TODStart>0</TODStart>
    <TODEnd>0</TODEnd>
    <TODMode>0</TODMode>
    <KillReset>1</KillReset>
    <ExternalTriggering>False</ExternalTriggering>
    <SequentialSpawning>-1</SequentialSpawning>
    <AllowGhostTriggering>False</AllowGhostTriggering>
    <AllowNPCTriggering>False</AllowNPCTriggering>
    <SpawnOnTrigger>False</SpawnOnTrigger>
    <SmartSpawning>False</SmartSpawning>
    <TickReset>False</TickReset>
    <Team>0</Team>
    <Amount>1</Amount>
    <IsGroup>False</IsGroup>
    <IsRunning>True</IsRunning>
    <IsHomeRangeRelative>True</IsHomeRangeRelative>
    <Objects2>drake:MX=1:SB=0:RT=0:TO=0:KL=0:RK=0:CA=1:DN=-1:DX=-1:SP=1:PR=-1</Objects2>
  </Points>
  <Points>
    <Name>tk</Name>
    <UniqueId>81ab44f4-5f6b-4004-adc7-ef606079a426</UniqueId>
    <Map>Felucca</Map>
    <X>5360</X>
    <Y>1581</Y>
    <Width>10</Width>
    <Height>10</Height>
    <CentreX>5365</CentreX>
    <CentreY>1586</CentreY>
    <CentreZ>0</CentreZ>
    <Range>5</Range>
    <MaxCount>1</MaxCount>
    <MinDelay>10</MinDelay>
    <MaxDelay>60</MaxDelay>
    <DelayInSec>True</DelayInSec>
    <Duration>0</Duration>
    <DespawnTime>0</DespawnTime>
    <ProximityRange>-1</ProximityRange>
    <ProximityTriggerSound>500</ProximityTriggerSound>
    <TriggerProbability>1</TriggerProbability>
    <InContainer>False</InContainer>
    <MinRefractory>0</MinRefractory>
    <MaxRefractory>0</MaxRefractory>
    <TODStart>0</TODStart>
    <TODEnd>0</TODEnd>
    <TODMode>0</TODMode>
    <KillReset>1</KillReset>
    <ExternalTriggering>False</ExternalTriggering>
    <SequentialSpawning>-1</SequentialSpawning>
    <AllowGhostTriggering>False</AllowGhostTriggering>
    <AllowNPCTriggering>False</AllowNPCTriggering>
    <SpawnOnTrigger>False</SpawnOnTrigger>
    <SmartSpawning>False</SmartSpawning>
    <TickReset>False</TickReset>
    <Team>0</Team>
    <Amount>1</Amount>
    <IsGroup>False</IsGroup>
    <IsRunning>True</IsRunning>
    <IsHomeRangeRelative>True</IsHomeRangeRelative>
    <Objects2>ophidianknight:MX=1:SB=0:RT=0:TO=0:KL=0:RK=0:CA=1:DN=-1:DX=-1:SP=1:PR=-1</Objects2>
  </Points>
  <Points>
    <Name>tk</Name>
    <UniqueId>874dba42-c580-4253-9a57-64a7ef6ab55e</UniqueId>
    <Map>Felucca</Map>
    <X>5349</X>
    <Y>1552</Y>
    <Width>10</Width>
    <Height>10</Height>
    <CentreX>5354</CentreX>
    <CentreY>1557</CentreY>
    <CentreZ>0</CentreZ>
    <Range>5</Range>
    <MaxCount>2</MaxCount>
    <MinDelay>10</MinDelay>
    <MaxDelay>60</MaxDelay>
    <DelayInSec>True</DelayInSec>
    <Duration>0</Duration>
    <DespawnTime>0</DespawnTime>
    <ProximityRange>-1</ProximityRange>
    <ProximityTriggerSound>500</ProximityTriggerSound>
    <TriggerProbability>1</TriggerProbability>
    <InContainer>False</InContainer>
    <MinRefractory>0</MinRefractory>
    <MaxRefractory>0</MaxRefractory>
    <TODStart>0</TODStart>
    <TODEnd>0</TODEnd>
    <TODMode>0</TODMode>
    <KillReset>1</KillReset>
    <ExternalTriggering>False</ExternalTriggering>
    <SequentialSpawning>-1</SequentialSpawning>
    <AllowGhostTriggering>False</AllowGhostTriggering>
    <AllowNPCTriggering>False</AllowNPCTriggering>
    <SpawnOnTrigger>False</SpawnOnTrigger>
    <SmartSpawning>False</SmartSpawning>
    <TickReset>False</TickReset>
    <Team>0</Team>
    <Amount>1</Amount>
    <IsGroup>False</IsGroup>
    <IsRunning>True</IsRunning>
    <IsHomeRangeRelative>True</IsHomeRangeRelative>
    <Objects2>ophidianwarrior:MX=2:SB=0:RT=0:TO=0:KL=0:RK=0:CA=1:DN=-1:DX=-1:SP=1:PR=-1</Objects2>
  </Points>
  <Points>
    <Name>tk</Name>
    <UniqueId>89b04d15-3575-4bc8-804d-f1683fb0f01b</UniqueId>
    <Map>Felucca</Map>
    <X>5308</X>
    <Y>1735</Y>
    <Width>10</Width>
    <Height>10</Height>
    <CentreX>5313</CentreX>
    <CentreY>1740</CentreY>
    <CentreZ>-28</CentreZ>
    <Range>5</Range>
    <MaxCount>1</MaxCount>
    <MinDelay>5</MinDelay>
    <MaxDelay>10</MaxDelay>
    <DelayInSec>False</DelayInSec>
    <Duration>0</Duration>
    <DespawnTime>0</DespawnTime>
    <ProximityRange>-1</ProximityRange>
    <ProximityTriggerSound>500</ProximityTriggerSound>
    <TriggerProbability>1</TriggerProbability>
    <InContainer>False</InContainer>
    <MinRefractory>0</MinRefractory>
    <MaxRefractory>0</MaxRefractory>
    <TODStart>0</TODStart>
    <TODEnd>0</TODEnd>
    <TODMode>0</TODMode>
    <KillReset>1</KillReset>
    <ExternalTriggering>False</ExternalTriggering>
    <SequentialSpawning>-1</SequentialSpawning>
    <AllowGhostTriggering>False</AllowGhostTriggering>
    <AllowNPCTriggering>False</AllowNPCTriggering>
    <SpawnOnTrigger>False</SpawnOnTrigger>
    <SmartSpawning>False</SmartSpawning>
    <TickReset>False</TickReset>
    <Team>0</Team>
    <Amount>1</Amount>
    <IsGroup>False</IsGroup>
    <IsRunning>True</IsRunning>
    <IsHomeRangeRelative>True</IsHomeRangeRelative>
    <Objects2>ophidianwarrior:MX=1:SB=0:RT=0:TO=0:KL=0:RK=0:CA=1:DN=-1:DX=-1:SP=1:PR=-1</Objects2>
  </Points>
  <Points>
    <Name>tk</Name>
    <UniqueId>918a1640-ab6f-4375-83bc-aab7697f1f8e</UniqueId>
    <Map>Felucca</Map>
    <X>5362</X>
    <Y>1587</Y>
    <Width>10</Width>
    <Height>10</Height>
    <CentreX>5367</CentreX>
    <CentreY>1592</CentreY>
    <CentreZ>0</CentreZ>
    <Range>5</Range>
    <MaxCount>1</MaxCount>
    <MinDelay>10</MinDelay>
    <MaxDelay>60</MaxDelay>
    <DelayInSec>True</DelayInSec>
    <Duration>0</Duration>
    <DespawnTime>0</DespawnTime>
    <ProximityRange>-1</ProximityRange>
    <ProximityTriggerSound>500</ProximityTriggerSound>
    <TriggerProbability>1</TriggerProbability>
    <InContainer>False</InContainer>
    <MinRefractory>0</MinRefractory>
    <MaxRefractory>0</MaxRefractory>
    <TODStart>0</TODStart>
    <TODEnd>0</TODEnd>
    <TODMode>0</TODMode>
    <KillReset>1</KillReset>
    <ExternalTriggering>False</ExternalTriggering>
    <SequentialSpawning>-1</SequentialSpawning>
    <AllowGhostTriggering>False</AllowGhostTriggering>
    <AllowNPCTriggering>False</AllowNPCTriggering>
    <SpawnOnTrigger>False</SpawnOnTrigger>
    <SmartSpawning>False</SmartSpawning>
    <TickReset>False</TickReset>
    <Team>0</Team>
    <Amount>1</Amount>
    <IsGroup>False</IsGroup>
    <IsRunning>True</IsRunning>
    <IsHomeRangeRelative>True</IsHomeRangeRelative>
    <Objects2>ophidianmatriarch:MX=1:SB=0:RT=0:TO=0:KL=0:RK=0:CA=1:DN=-1:DX=-1:SP=1:PR=-1</Objects2>
  </Points>
  <Points>
    <Name>tk</Name>
    <UniqueId>942b89de-3067-4340-abbf-d9c83a5b7c75</UniqueId>
    <Map>Felucca</Map>
    <X>5301</X>
    <Y>1608</Y>
    <Width>10</Width>
    <Height>10</Height>
    <CentreX>5306</CentreX>
    <CentreY>1613</CentreY>
    <CentreZ>0</CentreZ>
    <Range>5</Range>
    <MaxCount>1</MaxCount>
    <MinDelay>5</MinDelay>
    <MaxDelay>10</MaxDelay>
    <DelayInSec>False</DelayInSec>
    <Duration>0</Duration>
    <DespawnTime>0</DespawnTime>
    <ProximityRange>-1</ProximityRange>
    <ProximityTriggerSound>500</ProximityTriggerSound>
    <TriggerProbability>1</TriggerProbability>
    <InContainer>False</InContainer>
    <MinRefractory>0</MinRefractory>
    <MaxRefractory>0</MaxRefractory>
    <TODStart>0</TODStart>
    <TODEnd>0</TODEnd>
    <TODMode>0</TODMode>
    <KillReset>1</KillReset>
    <ExternalTriggering>False</ExternalTriggering>
    <SequentialSpawning>-1</SequentialSpawning>
    <AllowGhostTriggering>False</AllowGhostTriggering>
    <AllowNPCTriggering>False</AllowNPCTriggering>
    <SpawnOnTrigger>False</SpawnOnTrigger>
    <SmartSpawning>False</SmartSpawning>
    <TickReset>False</TickReset>
    <Team>0</Team>
    <Amount>1</Amount>
    <IsGroup>False</IsGroup>
    <IsRunning>True</IsRunning>
    <IsHomeRangeRelative>True</IsHomeRangeRelative>
    <Objects2>terathandrone:MX=1:SB=0:RT=0:TO=0:KL=0:RK=0:CA=1:DN=-1:DX=-1:SP=1:PR=-1</Objects2>
  </Points>
  <Points>
    <Name>tk</Name>
    <UniqueId>aa7ced12-5b95-4da3-be4c-833d859db543</UniqueId>
    <Map>Felucca</Map>
    <X>5324</X>
    <Y>1711</Y>
    <Width>10</Width>
    <Height>10</Height>
    <CentreX>5329</CentreX>
    <CentreY>1716</CentreY>
    <CentreZ>-47</CentreZ>
    <Range>5</Range>
    <MaxCount>1</MaxCount>
    <MinDelay>5</MinDelay>
    <MaxDelay>10</MaxDelay>
    <DelayInSec>False</DelayInSec>
    <Duration>0</Duration>
    <DespawnTime>0</DespawnTime>
    <ProximityRange>-1</ProximityRange>
    <ProximityTriggerSound>500</ProximityTriggerSound>
    <TriggerProbability>1</TriggerProbability>
    <InContainer>False</InContainer>
    <MinRefractory>0</MinRefractory>
    <MaxRefractory>0</MaxRefractory>
    <TODStart>0</TODStart>
    <TODEnd>0</TODEnd>
    <TODMode>0</TODMode>
    <KillReset>1</KillReset>
    <ExternalTriggering>False</ExternalTriggering>
    <SequentialSpawning>-1</SequentialSpawning>
    <AllowGhostTriggering>False</AllowGhostTriggering>
    <AllowNPCTriggering>False</AllowNPCTriggering>
    <SpawnOnTrigger>False</SpawnOnTrigger>
    <SmartSpawning>False</SmartSpawning>
    <TickReset>False</TickReset>
    <Team>0</Team>
    <Amount>1</Amount>
    <IsGroup>False</IsGroup>
    <IsRunning>True</IsRunning>
    <IsHomeRangeRelative>True</IsHomeRangeRelative>
    <Objects2>ophidianwarrior:MX=1:SB=0:RT=0:TO=0:KL=0:RK=0:CA=1:DN=-1:DX=-1:SP=1:PR=-1</Objects2>
  </Points>
  <Points>
    <Name>tk</Name>
    <UniqueId>ad53cc58-c251-42fb-994b-b16893faef6e</UniqueId>
    <Map>Felucca</Map>
    <X>5163</X>
    <Y>1680</Y>
    <Width>30</Width>
    <Height>30</Height>
    <CentreX>5178</CentreX>
    <CentreY>1695</CentreY>
    <CentreZ>2</CentreZ>
    <Range>15</Range>
    <MaxCount>3</MaxCount>
    <MinDelay>5</MinDelay>
    <MaxDelay>10</MaxDelay>
    <DelayInSec>False</DelayInSec>
    <Duration>0</Duration>
    <DespawnTime>0</DespawnTime>
    <ProximityRange>-1</ProximityRange>
    <ProximityTriggerSound>500</ProximityTriggerSound>
    <TriggerProbability>1</TriggerProbability>
    <InContainer>False</InContainer>
    <MinRefractory>0</MinRefractory>
    <MaxRefractory>0</MaxRefractory>
    <TODStart>0</TODStart>
    <TODEnd>0</TODEnd>
    <TODMode>0</TODMode>
    <KillReset>1</KillReset>
    <ExternalTriggering>False</ExternalTriggering>
    <SequentialSpawning>-1</SequentialSpawning>
    <AllowGhostTriggering>False</AllowGhostTriggering>
    <AllowNPCTriggering>False</AllowNPCTriggering>
    <SpawnOnTrigger>False</SpawnOnTrigger>
    <SmartSpawning>False</SmartSpawning>
    <TickReset>False</TickReset>
    <Team>0</Team>
    <Amount>1</Amount>
    <IsGroup>False</IsGroup>
    <IsRunning>True</IsRunning>
    <IsHomeRangeRelative>True</IsHomeRangeRelative>
    <Objects2>ophidianwarrior:MX=3:SB=0:RT=0:TO=0:KL=0:RK=0:CA=1:DN=-1:DX=-1:SP=1:PR=-1</Objects2>
  </Points>
  <Points>
    <Name>tk</Name>
    <UniqueId>b0d871c1-5766-4898-9504-c49434e5c3f7</UniqueId>
    <Map>Felucca</Map>
    <X>5310</X>
    <Y>1749</Y>
    <Width>10</Width>
    <Height>10</Height>
    <CentreX>5315</CentreX>
    <CentreY>1754</CentreY>
    <CentreZ>-48</CentreZ>
    <Range>12</Range>
    <MaxCount>1</MaxCount>
    <MinDelay>5</MinDelay>
    <MaxDelay>10</MaxDelay>
    <DelayInSec>False</DelayInSec>
    <Duration>0</Duration>
    <DespawnTime>0</DespawnTime>
    <ProximityRange>-1</ProximityRange>
    <ProximityTriggerSound>500</ProximityTriggerSound>
    <TriggerProbability>1</TriggerProbability>
    <InContainer>False</InContainer>
    <MinRefractory>0</MinRefractory>
    <MaxRefractory>0</MaxRefractory>
    <TODStart>0</TODStart>
    <TODEnd>0</TODEnd>
    <TODMode>0</TODMode>
    <KillReset>1</KillReset>
    <ExternalTriggering>False</ExternalTriggering>
    <SequentialSpawning>-1</SequentialSpawning>
    <AllowGhostTriggering>False</AllowGhostTriggering>
    <AllowNPCTriggering>False</AllowNPCTriggering>
    <SpawnOnTrigger>False</SpawnOnTrigger>
    <SmartSpawning>False</SmartSpawning>
    <TickReset>False</TickReset>
    <Team>0</Team>
    <Amount>1</Amount>
    <IsGroup>False</IsGroup>
    <IsRunning>True</IsRunning>
    <IsHomeRangeRelative>True</IsHomeRangeRelative>
    <Objects2>dragon:MX=1:SB=0:RT=0:TO=0:KL=0:RK=0:CA=1:DN=-1:DX=-1:SP=1:PR=-1</Objects2>
  </Points>
  <Points>
    <Name>tk</Name>
    <UniqueId>b27cbfc8-3dd7-4a26-a1bc-7e9e08149b8c</UniqueId>
    <Map>Felucca</Map>
    <X>5340</X>
    <Y>1557</Y>
    <Width>10</Width>
    <Height>10</Height>
    <CentreX>5345</CentreX>
    <CentreY>1562</CentreY>
    <CentreZ>0</CentreZ>
    <Range>5</Range>
    <MaxCount>3</MaxCount>
    <MinDelay>10</MinDelay>
    <MaxDelay>60</MaxDelay>
    <DelayInSec>True</DelayInSec>
    <Duration>0</Duration>
    <DespawnTime>0</DespawnTime>
    <ProximityRange>-1</ProximityRange>
    <ProximityTriggerSound>500</ProximityTriggerSound>
    <TriggerProbability>1</TriggerProbability>
    <InContainer>False</InContainer>
    <MinRefractory>0</MinRefractory>
    <MaxRefractory>0</MaxRefractory>
    <TODStart>0</TODStart>
    <TODEnd>0</TODEnd>
    <TODMode>0</TODMode>
    <KillReset>1</KillReset>
    <ExternalTriggering>False</ExternalTriggering>
    <SequentialSpawning>-1</SequentialSpawning>
    <AllowGhostTriggering>False</AllowGhostTriggering>
    <AllowNPCTriggering>False</AllowNPCTriggering>
    <SpawnOnTrigger>False</SpawnOnTrigger>
    <SmartSpawning>False</SmartSpawning>
    <TickReset>False</TickReset>
    <Team>0</Team>
    <Amount>1</Amount>
    <IsGroup>False</IsGroup>
    <IsRunning>True</IsRunning>
    <IsHomeRangeRelative>True</IsHomeRangeRelative>
    <Objects2>ophidianwarrior:MX=3:SB=0:RT=0:TO=0:KL=0:RK=0:CA=1:DN=-1:DX=-1:SP=1:PR=-1</Objects2>
  </Points>
  <Points>
    <Name>tk</Name>
    <UniqueId>bd8ff5e7-e969-4bc9-b021-3a32d65246b5</UniqueId>
    <Map>Felucca</Map>
    <X>5361</X>
    <Y>1610</Y>
    <Width>10</Width>
    <Height>10</Height>
    <CentreX>5366</CentreX>
    <CentreY>1615</CentreY>
    <CentreZ>0</CentreZ>
    <Range>5</Range>
    <MaxCount>3</MaxCount>
    <MinDelay>5</MinDelay>
    <MaxDelay>10</MaxDelay>
    <DelayInSec>False</DelayInSec>
    <Duration>0</Duration>
    <DespawnTime>0</DespawnTime>
    <ProximityRange>-1</ProximityRange>
    <ProximityTriggerSound>500</ProximityTriggerSound>
    <TriggerProbability>1</TriggerProbability>
    <InContainer>False</InContainer>
    <MinRefractory>0</MinRefractory>
    <MaxRefractory>0</MaxRefractory>
    <TODStart>0</TODStart>
    <TODEnd>0</TODEnd>
    <TODMode>0</TODMode>
    <KillReset>1</KillReset>
    <ExternalTriggering>False</ExternalTriggering>
    <SequentialSpawning>-1</SequentialSpawning>
    <AllowGhostTriggering>False</AllowGhostTriggering>
    <AllowNPCTriggering>False</AllowNPCTriggering>
    <SpawnOnTrigger>False</SpawnOnTrigger>
    <SmartSpawning>False</SmartSpawning>
    <TickReset>False</TickReset>
    <Team>0</Team>
    <Amount>1</Amount>
    <IsGroup>False</IsGroup>
    <IsRunning>True</IsRunning>
    <IsHomeRangeRelative>True</IsHomeRangeRelative>
    <Objects2>terathandrone:MX=3:SB=0:RT=0:TO=0:KL=0:RK=0:CA=1:DN=-1:DX=-1:SP=1:PR=-1</Objects2>
  </Points>
  <Points>
    <Name>tk</Name>
    <UniqueId>bddebd47-6792-410a-b297-2d4422de3591</UniqueId>
    <Map>Felucca</Map>
    <X>5310</X>
    <Y>1600</Y>
    <Width>10</Width>
    <Height>10</Height>
    <CentreX>5315</CentreX>
    <CentreY>1605</CentreY>
    <CentreZ>0</CentreZ>
    <Range>5</Range>
    <MaxCount>1</MaxCount>
    <MinDelay>5</MinDelay>
    <MaxDelay>10</MaxDelay>
    <DelayInSec>False</DelayInSec>
    <Duration>0</Duration>
    <DespawnTime>0</DespawnTime>
    <ProximityRange>-1</ProximityRange>
    <ProximityTriggerSound>500</ProximityTriggerSound>
    <TriggerProbability>1</TriggerProbability>
    <InContainer>False</InContainer>
    <MinRefractory>0</MinRefractory>
    <MaxRefractory>0</MaxRefractory>
    <TODStart>0</TODStart>
    <TODEnd>0</TODEnd>
    <TODMode>0</TODMode>
    <KillReset>1</KillReset>
    <ExternalTriggering>False</ExternalTriggering>
    <SequentialSpawning>-1</SequentialSpawning>
    <AllowGhostTriggering>False</AllowGhostTriggering>
    <AllowNPCTriggering>False</AllowNPCTriggering>
    <SpawnOnTrigger>False</SpawnOnTrigger>
    <SmartSpawning>False</SmartSpawning>
    <TickReset>False</TickReset>
    <Team>0</Team>
    <Amount>1</Amount>
    <IsGroup>False</IsGroup>
    <IsRunning>True</IsRunning>
    <IsHomeRangeRelative>True</IsHomeRangeRelative>
    <Objects2>terathanwarrior:MX=1:SB=0:RT=0:TO=0:KL=0:RK=0:CA=1:DN=-1:DX=-1:SP=1:PR=-1</Objects2>
  </Points>
  <Points>
    <Name>tk</Name>
    <UniqueId>c054d6c8-d8da-4c89-b0aa-c5a05971118f</UniqueId>
    <Map>Felucca</Map>
    <X>5307</X>
    <Y>1545</Y>
    <Width>10</Width>
    <Height>10</Height>
    <CentreX>5312</CentreX>
    <CentreY>1550</CentreY>
    <CentreZ>0</CentreZ>
    <Range>5</Range>
    <MaxCount>1</MaxCount>
    <MinDelay>5</MinDelay>
    <MaxDelay>10</MaxDelay>
    <DelayInSec>False</DelayInSec>
    <Duration>0</Duration>
    <DespawnTime>0</DespawnTime>
    <ProximityRange>-1</ProximityRange>
    <ProximityTriggerSound>500</ProximityTriggerSound>
    <TriggerProbability>1</TriggerProbability>
    <InContainer>False</InContainer>
    <MinRefractory>0</MinRefractory>
    <MaxRefractory>0</MaxRefractory>
    <TODStart>0</TODStart>
    <TODEnd>0</TODEnd>
    <TODMode>0</TODMode>
    <KillReset>1</KillReset>
    <ExternalTriggering>False</ExternalTriggering>
    <SequentialSpawning>-1</SequentialSpawning>
    <AllowGhostTriggering>False</AllowGhostTriggering>
    <AllowNPCTriggering>False</AllowNPCTriggering>
    <SpawnOnTrigger>False</SpawnOnTrigger>
    <SmartSpawning>False</SmartSpawning>
    <TickReset>False</TickReset>
    <Team>0</Team>
    <Amount>1</Amount>
    <IsGroup>False</IsGroup>
    <IsRunning>True</IsRunning>
    <IsHomeRangeRelative>True</IsHomeRangeRelative>
    <Objects2>giantspider:MX=1:SB=0:RT=0:TO=0:KL=0:RK=0:CA=1:DN=-1:DX=-1:SP=1:PR=-1</Objects2>
  </Points>
  <Points>
    <Name>tk</Name>
    <UniqueId>c2d2efe6-5541-4b46-9624-72af6e001291</UniqueId>
    <Map>Felucca</Map>
    <X>5247</X>
    <Y>1675</Y>
    <Width>40</Width>
    <Height>40</Height>
    <CentreX>5267</CentreX>
    <CentreY>1695</CentreY>
    <CentreZ>0</CentreZ>
    <Range>35</Range>
    <MaxCount>3</MaxCount>
    <MinDelay>5</MinDelay>
    <MaxDelay>10</MaxDelay>
    <DelayInSec>False</DelayInSec>
    <Duration>0</Duration>
    <DespawnTime>0</DespawnTime>
    <ProximityRange>-1</ProximityRange>
    <ProximityTriggerSound>500</ProximityTriggerSound>
    <TriggerProbability>1</TriggerProbability>
    <InContainer>False</InContainer>
    <MinRefractory>0</MinRefractory>
    <MaxRefractory>0</MaxRefractory>
    <TODStart>0</TODStart>
    <TODEnd>0</TODEnd>
    <TODMode>0</TODMode>
    <KillReset>1</KillReset>
    <ExternalTriggering>False</ExternalTriggering>
    <SequentialSpawning>-1</SequentialSpawning>
    <AllowGhostTriggering>False</AllowGhostTriggering>
    <AllowNPCTriggering>False</AllowNPCTriggering>
    <SpawnOnTrigger>False</SpawnOnTrigger>
    <SmartSpawning>False</SmartSpawning>
    <TickReset>False</TickReset>
    <Team>0</Team>
    <Amount>1</Amount>
    <IsGroup>False</IsGroup>
    <IsRunning>True</IsRunning>
    <IsHomeRangeRelative>True</IsHomeRangeRelative>
    <Objects2>ophidianwarrior:MX=3:SB=0:RT=0:TO=0:KL=0:RK=0:CA=1:DN=-1:DX=-1:SP=1:PR=-1</Objects2>
  </Points>
  <Points>
    <Name>tk</Name>
    <UniqueId>c348b8b8-26e4-48b5-b5f9-da18ac2a2a80</UniqueId>
    <Map>Felucca</Map>
    <X>5342</X>
    <Y>1580</Y>
    <Width>2</Width>
    <Height>2</Height>
    <CentreX>5343</CentreX>
    <CentreY>1581</CentreY>
    <CentreZ>0</CentreZ>
    <Range>5</Range>
    <MaxCount>1</MaxCount>
    <MinDelay>10</MinDelay>
    <MaxDelay>60</MaxDelay>
    <DelayInSec>True</DelayInSec>
    <Duration>0</Duration>
    <DespawnTime>0</DespawnTime>
    <ProximityRange>-1</ProximityRange>
    <ProximityTriggerSound>500</ProximityTriggerSound>
    <TriggerProbability>1</TriggerProbability>
    <InContainer>False</InContainer>
    <MinRefractory>0</MinRefractory>
    <MaxRefractory>0</MaxRefractory>
    <TODStart>0</TODStart>
    <TODEnd>0</TODEnd>
    <TODMode>0</TODMode>
    <KillReset>1</KillReset>
    <ExternalTriggering>False</ExternalTriggering>
    <SequentialSpawning>-1</SequentialSpawning>
    <AllowGhostTriggering>False</AllowGhostTriggering>
    <AllowNPCTriggering>False</AllowNPCTriggering>
    <SpawnOnTrigger>False</SpawnOnTrigger>
    <SmartSpawning>False</SmartSpawning>
    <TickReset>False</TickReset>
    <Team>0</Team>
    <Amount>1</Amount>
    <IsGroup>False</IsGroup>
    <IsRunning>True</IsRunning>
    <IsHomeRangeRelative>True</IsHomeRangeRelative>
    <Objects2>ophidianmatriarch:MX=1:SB=0:RT=0:TO=0:KL=0:RK=0:CA=1:DN=-1:DX=-1:SP=1:PR=-1</Objects2>
  </Points>
  <Points>
    <Name>tk</Name>
    <UniqueId>c36f4dd2-3cf6-4311-a016-983c5bd7a4a5</UniqueId>
    <Map>Felucca</Map>
    <X>5325</X>
    <Y>1544</Y>
    <Width>10</Width>
    <Height>10</Height>
    <CentreX>5330</CentreX>
    <CentreY>1549</CentreY>
    <CentreZ>0</CentreZ>
    <Range>5</Range>
    <MaxCount>1</MaxCount>
    <MinDelay>10</MinDelay>
    <MaxDelay>60</MaxDelay>
    <DelayInSec>True</DelayInSec>
    <Duration>0</Duration>
    <DespawnTime>0</DespawnTime>
    <ProximityRange>-1</ProximityRange>
    <ProximityTriggerSound>500</ProximityTriggerSound>
    <TriggerProbability>1</TriggerProbability>
    <InContainer>False</InContainer>
    <MinRefractory>0</MinRefractory>
    <MaxRefractory>0</MaxRefractory>
    <TODStart>0</TODStart>
    <TODEnd>0</TODEnd>
    <TODMode>0</TODMode>
    <KillReset>1</KillReset>
    <ExternalTriggering>False</ExternalTriggering>
    <SequentialSpawning>-1</SequentialSpawning>
    <AllowGhostTriggering>False</AllowGhostTriggering>
    <AllowNPCTriggering>False</AllowNPCTriggering>
    <SpawnOnTrigger>False</SpawnOnTrigger>
    <SmartSpawning>False</SmartSpawning>
    <TickReset>False</TickReset>
    <Team>0</Team>
    <Amount>1</Amount>
    <IsGroup>False</IsGroup>
    <IsRunning>True</IsRunning>
    <IsHomeRangeRelative>True</IsHomeRangeRelative>
    <Objects2>ophidianarchmage:MX=1:SB=0:RT=0:TO=0:KL=0:RK=0:CA=1:DN=-1:DX=-1:SP=1:PR=-1</Objects2>
  </Points>
  <Points>
    <Name>tk</Name>
    <UniqueId>c606da4c-70d7-4064-9ef1-f563b47f7aab</UniqueId>
    <Map>Felucca</Map>
    <X>5242</X>
    <Y>1655</Y>
    <Width>50</Width>
    <Height>50</Height>
    <CentreX>5267</CentreX>
    <CentreY>1680</CentreY>
    <CentreZ>0</CentreZ>
    <Range>35</Range>
    <MaxCount>1</MaxCount>
    <MinDelay>5</MinDelay>
    <MaxDelay>10</MaxDelay>
    <DelayInSec>False</DelayInSec>
    <Duration>0</Duration>
    <DespawnTime>0</DespawnTime>
    <ProximityRange>-1</ProximityRange>
    <ProximityTriggerSound>500</ProximityTriggerSound>
    <TriggerProbability>1</TriggerProbability>
    <InContainer>False</InContainer>
    <MinRefractory>0</MinRefractory>
    <MaxRefractory>0</MaxRefractory>
    <TODStart>0</TODStart>
    <TODEnd>0</TODEnd>
    <TODMode>0</TODMode>
    <KillReset>1</KillReset>
    <ExternalTriggering>False</ExternalTriggering>
    <SequentialSpawning>-1</SequentialSpawning>
    <AllowGhostTriggering>False</AllowGhostTriggering>
    <AllowNPCTriggering>False</AllowNPCTriggering>
    <SpawnOnTrigger>False</SpawnOnTrigger>
    <SmartSpawning>False</SmartSpawning>
    <TickReset>False</TickReset>
    <Team>0</Team>
    <Amount>1</Amount>
    <IsGroup>False</IsGroup>
    <IsRunning>True</IsRunning>
    <IsHomeRangeRelative>True</IsHomeRangeRelative>
    <Objects2>ophidianknight:MX=1:SB=0:RT=0:TO=0:KL=0:RK=0:CA=1:DN=-1:DX=-1:SP=1:PR=-1</Objects2>
  </Points>
  <Points>
    <Name>tk</Name>
    <UniqueId>c75dffe4-519c-4e41-8ceb-2331d66d6db9</UniqueId>
    <Map>Felucca</Map>
    <X>5340</X>
    <Y>1539</Y>
    <Width>10</Width>
    <Height>10</Height>
    <CentreX>5345</CentreX>
    <CentreY>1544</CentreY>
    <CentreZ>0</CentreZ>
    <Range>8</Range>
    <MaxCount>1</MaxCount>
    <MinDelay>10</MinDelay>
    <MaxDelay>60</MaxDelay>
    <DelayInSec>True</DelayInSec>
    <Duration>0</Duration>
    <DespawnTime>0</DespawnTime>
    <ProximityRange>-1</ProximityRange>
    <ProximityTriggerSound>500</ProximityTriggerSound>
    <TriggerProbability>1</TriggerProbability>
    <InContainer>False</InContainer>
    <MinRefractory>0</MinRefractory>
    <MaxRefractory>0</MaxRefractory>
    <TODStart>0</TODStart>
    <TODEnd>0</TODEnd>
    <TODMode>0</TODMode>
    <KillReset>1</KillReset>
    <ExternalTriggering>False</ExternalTriggering>
    <SequentialSpawning>-1</SequentialSpawning>
    <AllowGhostTriggering>False</AllowGhostTriggering>
    <AllowNPCTriggering>False</AllowNPCTriggering>
    <SpawnOnTrigger>False</SpawnOnTrigger>
    <SmartSpawning>False</SmartSpawning>
    <TickReset>False</TickReset>
    <Team>0</Team>
    <Amount>1</Amount>
    <IsGroup>False</IsGroup>
    <IsRunning>True</IsRunning>
    <IsHomeRangeRelative>True</IsHomeRangeRelative>
    <Objects2>balron:MX=1:SB=0:RT=0:TO=0:KL=0:RK=0:CA=1:DN=-1:DX=-1:SP=1:PR=-1</Objects2>
  </Points>
  <Points>
    <Name>tk</Name>
    <UniqueId>c800a544-975a-41e4-ae81-db25e39e6979</UniqueId>
    <Map>Felucca</Map>
    <X>5328</X>
    <Y>1724</Y>
    <Width>32</Width>
    <Height>32</Height>
    <CentreX>5344</CentreX>
    <CentreY>1740</CentreY>
    <CentreZ>-67</CentreZ>
    <Range>16</Range>
    <MaxCount>1</MaxCount>
    <MinDelay>5</MinDelay>
    <MaxDelay>10</MaxDelay>
    <DelayInSec>False</DelayInSec>
    <Duration>0</Duration>
    <DespawnTime>0</DespawnTime>
    <ProximityRange>-1</ProximityRange>
    <ProximityTriggerSound>500</ProximityTriggerSound>
    <TriggerProbability>1</TriggerProbability>
    <InContainer>False</InContainer>
    <MinRefractory>0</MinRefractory>
    <MaxRefractory>0</MaxRefractory>
    <TODStart>0</TODStart>
    <TODEnd>0</TODEnd>
    <TODMode>0</TODMode>
    <KillReset>1</KillReset>
    <ExternalTriggering>False</ExternalTriggering>
    <SequentialSpawning>-1</SequentialSpawning>
    <AllowGhostTriggering>False</AllowGhostTriggering>
    <AllowNPCTriggering>False</AllowNPCTriggering>
    <SpawnOnTrigger>False</SpawnOnTrigger>
    <SmartSpawning>False</SmartSpawning>
    <TickReset>False</TickReset>
    <Team>0</Team>
    <Amount>1</Amount>
    <IsGroup>False</IsGroup>
    <IsRunning>True</IsRunning>
    <IsHomeRangeRelative>True</IsHomeRangeRelative>
    <Objects2>nightmare:MX=1:SB=0:RT=0:TO=0:KL=0:RK=0:CA=1:DN=-1:DX=-1:SP=1:PR=-1</Objects2>
  </Points>
  <Points>
    <Name>tk</Name>
    <UniqueId>c93c28ad-3fd9-4e37-983b-1771d35824b6</UniqueId>
    <Map>Felucca</Map>
    <X>5280</X>
    <Y>1545</Y>
    <Width>10</Width>
    <Height>10</Height>
    <CentreX>5285</CentreX>
    <CentreY>1550</CentreY>
    <CentreZ>0</CentreZ>
    <Range>5</Range>
    <MaxCount>1</MaxCount>
    <MinDelay>5</MinDelay>
    <MaxDelay>10</MaxDelay>
    <DelayInSec>False</DelayInSec>
    <Duration>0</Duration>
    <DespawnTime>0</DespawnTime>
    <ProximityRange>-1</ProximityRange>
    <ProximityTriggerSound>500</ProximityTriggerSound>
    <TriggerProbability>1</TriggerProbability>
    <InContainer>False</InContainer>
    <MinRefractory>0</MinRefractory>
    <MaxRefractory>0</MaxRefractory>
    <TODStart>0</TODStart>
    <TODEnd>0</TODEnd>
    <TODMode>0</TODMode>
    <KillReset>1</KillReset>
    <ExternalTriggering>False</ExternalTriggering>
    <SequentialSpawning>-1</SequentialSpawning>
    <AllowGhostTriggering>False</AllowGhostTriggering>
    <AllowNPCTriggering>False</AllowNPCTriggering>
    <SpawnOnTrigger>False</SpawnOnTrigger>
    <SmartSpawning>False</SmartSpawning>
    <TickReset>False</TickReset>
    <Team>0</Team>
    <Amount>1</Amount>
    <IsGroup>False</IsGroup>
    <IsRunning>True</IsRunning>
    <IsHomeRangeRelative>True</IsHomeRangeRelative>
    <Objects2>terathandrone:MX=1:SB=0:RT=0:TO=0:KL=0:RK=0:CA=1:DN=-1:DX=-1:SP=1:PR=-1</Objects2>
  </Points>
  <Points>
    <Name>tk</Name>
    <UniqueId>d4b6be0d-822a-4ee6-bf26-eed77d876c1f</UniqueId>
    <Map>Felucca</Map>
    <X>5310</X>
    <Y>1623</Y>
    <Width>10</Width>
    <Height>10</Height>
    <CentreX>5315</CentreX>
    <CentreY>1628</CentreY>
    <CentreZ>0</CentreZ>
    <Range>5</Range>
    <MaxCount>1</MaxCount>
    <MinDelay>5</MinDelay>
    <MaxDelay>10</MaxDelay>
    <DelayInSec>False</DelayInSec>
    <Duration>0</Duration>
    <DespawnTime>0</DespawnTime>
    <ProximityRange>-1</ProximityRange>
    <ProximityTriggerSound>500</ProximityTriggerSound>
    <TriggerProbability>1</TriggerProbability>
    <InContainer>False</InContainer>
    <MinRefractory>0</MinRefractory>
    <MaxRefractory>0</MaxRefractory>
    <TODStart>0</TODStart>
    <TODEnd>0</TODEnd>
    <TODMode>0</TODMode>
    <KillReset>1</KillReset>
    <ExternalTriggering>False</ExternalTriggering>
    <SequentialSpawning>-1</SequentialSpawning>
    <AllowGhostTriggering>False</AllowGhostTriggering>
    <AllowNPCTriggering>False</AllowNPCTriggering>
    <SpawnOnTrigger>False</SpawnOnTrigger>
    <SmartSpawning>False</SmartSpawning>
    <TickReset>False</TickReset>
    <Team>0</Team>
    <Amount>1</Amount>
    <IsGroup>False</IsGroup>
    <IsRunning>True</IsRunning>
    <IsHomeRangeRelative>True</IsHomeRangeRelative>
    <Objects2>terathandrone:MX=1:SB=0:RT=0:TO=0:KL=0:RK=0:CA=1:DN=-1:DX=-1:SP=1:PR=-1</Objects2>
  </Points>
  <Points>
    <Name>tk</Name>
    <UniqueId>d6f071e1-2365-494d-935e-9321c030074b</UniqueId>
    <Map>Felucca</Map>
    <X>5332</X>
    <Y>1731</Y>
    <Width>32</Width>
    <Height>32</Height>
    <CentreX>5348</CentreX>
    <CentreY>1747</CentreY>
    <CentreZ>-77</CentreZ>
    <Range>16</Range>
    <MaxCount>1</MaxCount>
    <MinDelay>5</MinDelay>
    <MaxDelay>10</MaxDelay>
    <DelayInSec>False</DelayInSec>
    <Duration>0</Duration>
    <DespawnTime>0</DespawnTime>
    <ProximityRange>-1</ProximityRange>
    <ProximityTriggerSound>500</ProximityTriggerSound>
    <TriggerProbability>1</TriggerProbability>
    <InContainer>False</InContainer>
    <MinRefractory>0</MinRefractory>
    <MaxRefractory>0</MaxRefractory>
    <TODStart>0</TODStart>
    <TODEnd>0</TODEnd>
    <TODMode>0</TODMode>
    <KillReset>1</KillReset>
    <ExternalTriggering>False</ExternalTriggering>
    <SequentialSpawning>-1</SequentialSpawning>
    <AllowGhostTriggering>False</AllowGhostTriggering>
    <AllowNPCTriggering>False</AllowNPCTriggering>
    <SpawnOnTrigger>False</SpawnOnTrigger>
    <SmartSpawning>False</SmartSpawning>
    <TickReset>False</TickReset>
    <Team>0</Team>
    <Amount>1</Amount>
    <IsGroup>False</IsGroup>
    <IsRunning>True</IsRunning>
    <IsHomeRangeRelative>True</IsHomeRangeRelative>
    <Objects2>greaterdragon:MX=1:SB=0:RT=0:TO=0:KL=0:RK=0:CA=1:DN=-1:DX=-1:SP=1:PR=-1</Objects2>
  </Points>
  <Points>
    <Name>tk</Name>
    <UniqueId>dc059a0e-f3a4-4766-ab27-476fd85d4c66</UniqueId>
    <Map>Felucca</Map>
    <X>5343</X>
    <Y>1550</Y>
    <Width>4</Width>
    <Height>4</Height>
    <CentreX>5345</CentreX>
    <CentreY>1552</CentreY>
    <CentreZ>0</CentreZ>
    <Range>4</Range>
    <MaxCount>2</MaxCount>
    <MinDelay>10</MinDelay>
    <MaxDelay>60</MaxDelay>
    <DelayInSec>True</DelayInSec>
    <Duration>0</Duration>
    <DespawnTime>0</DespawnTime>
    <ProximityRange>-1</ProximityRange>
    <ProximityTriggerSound>500</ProximityTriggerSound>
    <TriggerProbability>1</TriggerProbability>
    <InContainer>False</InContainer>
    <MinRefractory>0</MinRefractory>
    <MaxRefractory>0</MaxRefractory>
    <TODStart>0</TODStart>
    <TODEnd>0</TODEnd>
    <TODMode>0</TODMode>
    <KillReset>1</KillReset>
    <ExternalTriggering>False</ExternalTriggering>
    <SequentialSpawning>-1</SequentialSpawning>
    <AllowGhostTriggering>False</AllowGhostTriggering>
    <AllowNPCTriggering>False</AllowNPCTriggering>
    <SpawnOnTrigger>False</SpawnOnTrigger>
    <SmartSpawning>False</SmartSpawning>
    <TickReset>False</TickReset>
    <Team>0</Team>
    <Amount>1</Amount>
    <IsGroup>False</IsGroup>
    <IsRunning>True</IsRunning>
    <IsHomeRangeRelative>True</IsHomeRangeRelative>
    <Objects2>ophidianwarrior:MX=2:SB=0:RT=0:TO=0:KL=0:RK=0:CA=1:DN=-1:DX=-1:SP=1:PR=-1</Objects2>
  </Points>
  <Points>
    <Name>tk</Name>
    <UniqueId>df6609b3-5ef3-4712-8d4b-381e6d23b5f6</UniqueId>
    <Map>Felucca</Map>
    <X>5198</X>
    <Y>1684</Y>
    <Width>10</Width>
    <Height>10</Height>
    <CentreX>5203</CentreX>
    <CentreY>1689</CentreY>
    <CentreZ>-1</CentreZ>
    <Range>20</Range>
    <MaxCount>2</MaxCount>
    <MinDelay>5</MinDelay>
    <MaxDelay>10</MaxDelay>
    <DelayInSec>False</DelayInSec>
    <Duration>0</Duration>
    <DespawnTime>0</DespawnTime>
    <ProximityRange>-1</ProximityRange>
    <ProximityTriggerSound>500</ProximityTriggerSound>
    <TriggerProbability>1</TriggerProbability>
    <InContainer>False</InContainer>
    <MinRefractory>0</MinRefractory>
    <MaxRefractory>0</MaxRefractory>
    <TODStart>0</TODStart>
    <TODEnd>0</TODEnd>
    <TODMode>0</TODMode>
    <KillReset>1</KillReset>
    <ExternalTriggering>False</ExternalTriggering>
    <SequentialSpawning>-1</SequentialSpawning>
    <AllowGhostTriggering>False</AllowGhostTriggering>
    <AllowNPCTriggering>False</AllowNPCTriggering>
    <SpawnOnTrigger>False</SpawnOnTrigger>
    <SmartSpawning>False</SmartSpawning>
    <TickReset>False</TickReset>
    <Team>0</Team>
    <Amount>1</Amount>
    <IsGroup>False</IsGroup>
    <IsRunning>True</IsRunning>
    <IsHomeRangeRelative>True</IsHomeRangeRelative>
    <Objects2>ophidianmage:MX=1:SB=0:RT=0:TO=0:KL=0:RK=0:CA=1:DN=-1:DX=-1:SP=1:PR=-1:OBJ=ophidianwarrior:MX=1:SB=0:RT=0:TO=0:KL=0:RK=0:CA=1:DN=-1:DX=-1:SP=1:PR=-1</Objects2>
  </Points>
  <Points>
    <Name>tk</Name>
    <UniqueId>e03f245b-67f7-4826-b7e6-65245f1ca0c0</UniqueId>
    <Map>Felucca</Map>
    <X>5298</X>
    <Y>1602</Y>
    <Width>14</Width>
    <Height>14</Height>
    <CentreX>5305</CentreX>
    <CentreY>1609</CentreY>
    <CentreZ>0</CentreZ>
    <Range>10</Range>
    <MaxCount>4</MaxCount>
    <MinDelay>5</MinDelay>
    <MaxDelay>10</MaxDelay>
    <DelayInSec>False</DelayInSec>
    <Duration>0</Duration>
    <DespawnTime>0</DespawnTime>
    <ProximityRange>-1</ProximityRange>
    <ProximityTriggerSound>500</ProximityTriggerSound>
    <TriggerProbability>1</TriggerProbability>
    <InContainer>False</InContainer>
    <MinRefractory>0</MinRefractory>
    <MaxRefractory>0</MaxRefractory>
    <TODStart>0</TODStart>
    <TODEnd>0</TODEnd>
    <TODMode>0</TODMode>
    <KillReset>1</KillReset>
    <ExternalTriggering>False</ExternalTriggering>
    <SequentialSpawning>-1</SequentialSpawning>
    <AllowGhostTriggering>False</AllowGhostTriggering>
    <AllowNPCTriggering>False</AllowNPCTriggering>
    <SpawnOnTrigger>False</SpawnOnTrigger>
    <SmartSpawning>False</SmartSpawning>
    <TickReset>False</TickReset>
    <Team>0</Team>
    <Amount>1</Amount>
    <IsGroup>False</IsGroup>
    <IsRunning>True</IsRunning>
    <IsHomeRangeRelative>True</IsHomeRangeRelative>
    <Objects2>ophidianknight:MX=4:SB=0:RT=0:TO=0:KL=0:RK=0:CA=1:DN=-1:DX=-1:SP=1:PR=-1</Objects2>
  </Points>
  <Points>
    <Name>tk</Name>
    <UniqueId>e45f8270-979b-48d8-8910-50de19e8ddb0</UniqueId>
    <Map>Felucca</Map>
    <X>5315</X>
    <Y>1563</Y>
    <Width>2</Width>
    <Height>2</Height>
    <CentreX>5316</CentreX>
    <CentreY>1564</CentreY>
    <CentreZ>0</CentreZ>
    <Range>30</Range>
    <MaxCount>1</MaxCount>
    <MinDelay>5</MinDelay>
    <MaxDelay>10</MaxDelay>
    <DelayInSec>False</DelayInSec>
    <Duration>0</Duration>
    <DespawnTime>0</DespawnTime>
    <ProximityRange>-1</ProximityRange>
    <ProximityTriggerSound>500</ProximityTriggerSound>
    <TriggerProbability>1</TriggerProbability>
    <InContainer>False</InContainer>
    <MinRefractory>0</MinRefractory>
    <MaxRefractory>0</MaxRefractory>
    <TODStart>0</TODStart>
    <TODEnd>0</TODEnd>
    <TODMode>0</TODMode>
    <KillReset>1</KillReset>
    <ExternalTriggering>False</ExternalTriggering>
    <SequentialSpawning>-1</SequentialSpawning>
    <AllowGhostTriggering>False</AllowGhostTriggering>
    <AllowNPCTriggering>False</AllowNPCTriggering>
    <SpawnOnTrigger>False</SpawnOnTrigger>
    <SmartSpawning>False</SmartSpawning>
    <TickReset>False</TickReset>
    <Team>0</Team>
    <Amount>1</Amount>
    <IsGroup>False</IsGroup>
    <IsRunning>True</IsRunning>
    <IsHomeRangeRelative>True</IsHomeRangeRelative>
    <Objects2>terathanavenger:MX=1:SB=0:RT=0:TO=0:KL=0:RK=0:CA=1:DN=-1:DX=-1:SP=1:PR=-1</Objects2>
  </Points>
  <Points>
    <Name>tk</Name>
    <UniqueId>f3430115-b9bb-421c-accb-704f1f8d3db9</UniqueId>
    <Map>Felucca</Map>
    <X>5320</X>
    <Y>1618</Y>
    <Width>10</Width>
    <Height>10</Height>
    <CentreX>5325</CentreX>
    <CentreY>1623</CentreY>
    <CentreZ>0</CentreZ>
    <Range>5</Range>
    <MaxCount>1</MaxCount>
    <MinDelay>5</MinDelay>
    <MaxDelay>10</MaxDelay>
    <DelayInSec>False</DelayInSec>
    <Duration>0</Duration>
    <DespawnTime>0</DespawnTime>
    <ProximityRange>-1</ProximityRange>
    <ProximityTriggerSound>500</ProximityTriggerSound>
    <TriggerProbability>1</TriggerProbability>
    <InContainer>False</InContainer>
    <MinRefractory>0</MinRefractory>
    <MaxRefractory>0</MaxRefractory>
    <TODStart>0</TODStart>
    <TODEnd>0</TODEnd>
    <TODMode>0</TODMode>
    <KillReset>1</KillReset>
    <ExternalTriggering>False</ExternalTriggering>
    <SequentialSpawning>-1</SequentialSpawning>
    <AllowGhostTriggering>False</AllowGhostTriggering>
    <AllowNPCTriggering>False</AllowNPCTriggering>
    <SpawnOnTrigger>False</SpawnOnTrigger>
    <SmartSpawning>False</SmartSpawning>
    <TickReset>False</TickReset>
    <Team>0</Team>
    <Amount>1</Amount>
    <IsGroup>False</IsGroup>
    <IsRunning>True</IsRunning>
    <IsHomeRangeRelative>True</IsHomeRangeRelative>
    <Objects2>terathandrone:MX=1:SB=0:RT=0:TO=0:KL=0:RK=0:CA=1:DN=-1:DX=-1:SP=1:PR=-1</Objects2>
  </Points>
  <Points>
    <Name>tk</Name>
    <UniqueId>f3ab09dc-0a0e-46df-8160-7181a7b3bec7</UniqueId>
    <Map>Felucca</Map>
    <X>5145</X>
    <Y>1657</Y>
    <Width>10</Width>
    <Height>10</Height>
    <CentreX>5150</CentreX>
    <CentreY>1662</CentreY>
    <CentreZ>0</CentreZ>
    <Range>25</Range>
    <MaxCount>2</MaxCount>
    <MinDelay>5</MinDelay>
    <MaxDelay>10</MaxDelay>
    <DelayInSec>False</DelayInSec>
    <Duration>0</Duration>
    <DespawnTime>0</DespawnTime>
    <ProximityRange>-1</ProximityRange>
    <ProximityTriggerSound>500</ProximityTriggerSound>
    <TriggerProbability>1</TriggerProbability>
    <InContainer>False</InContainer>
    <MinRefractory>0</MinRefractory>
    <MaxRefractory>0</MaxRefractory>
    <TODStart>0</TODStart>
    <TODEnd>0</TODEnd>
    <TODMode>0</TODMode>
    <KillReset>1</KillReset>
    <ExternalTriggering>False</ExternalTriggering>
    <SequentialSpawning>-1</SequentialSpawning>
    <AllowGhostTriggering>False</AllowGhostTriggering>
    <AllowNPCTriggering>False</AllowNPCTriggering>
    <SpawnOnTrigger>False</SpawnOnTrigger>
    <SmartSpawning>False</SmartSpawning>
    <TickReset>False</TickReset>
    <Team>0</Team>
    <Amount>1</Amount>
    <IsGroup>False</IsGroup>
    <IsRunning>True</IsRunning>
    <IsHomeRangeRelative>True</IsHomeRangeRelative>
    <Objects2>ophidianwarrior:MX=2:SB=0:RT=0:TO=0:KL=0:RK=0:CA=1:DN=-1:DX=-1:SP=1:PR=-1</Objects2>
  </Points>
  <Points>
    <Name>tk</Name>
    <UniqueId>f67c8710-e2d3-4aab-b217-ab64f2f54a2e</UniqueId>
    <Map>Felucca</Map>
    <X>5310</X>
    <Y>1674</Y>
    <Width>20</Width>
    <Height>20</Height>
    <CentreX>5320</CentreX>
    <CentreY>1684</CentreY>
    <CentreZ>-11</CentreZ>
    <Range>25</Range>
    <MaxCount>3</MaxCount>
    <MinDelay>5</MinDelay>
    <MaxDelay>10</MaxDelay>
    <DelayInSec>False</DelayInSec>
    <Duration>0</Duration>
    <DespawnTime>0</DespawnTime>
    <ProximityRange>-1</ProximityRange>
    <ProximityTriggerSound>500</ProximityTriggerSound>
    <TriggerProbability>1</TriggerProbability>
    <InContainer>False</InContainer>
    <MinRefractory>0</MinRefractory>
    <MaxRefractory>0</MaxRefractory>
    <TODStart>0</TODStart>
    <TODEnd>0</TODEnd>
    <TODMode>0</TODMode>
    <KillReset>1</KillReset>
    <ExternalTriggering>False</ExternalTriggering>
    <SequentialSpawning>-1</SequentialSpawning>
    <AllowGhostTriggering>False</AllowGhostTriggering>
    <AllowNPCTriggering>False</AllowNPCTriggering>
    <SpawnOnTrigger>False</SpawnOnTrigger>
    <SmartSpawning>False</SmartSpawning>
    <TickReset>False</TickReset>
    <Team>0</Team>
    <Amount>1</Amount>
    <IsGroup>False</IsGroup>
    <IsRunning>True</IsRunning>
    <IsHomeRangeRelative>True</IsHomeRangeRelative>
    <Objects2>ophidianwarrior:MX=3:SB=0:RT=0:TO=0:KL=0:RK=0:CA=1:DN=-1:DX=-1:SP=1:PR=-1</Objects2>
  </Points>
  <Points>
    <Name>tk</Name>
    <UniqueId>f86329b6-26ec-4ea5-9908-6a4757ff3216</UniqueId>
    <Map>Felucca</Map>
    <X>5328</X>
    <Y>1732</Y>
    <Width>32</Width>
    <Height>32</Height>
    <CentreX>5344</CentreX>
    <CentreY>1748</CentreY>
    <CentreZ>-70</CentreZ>
    <Range>16</Range>
    <MaxCount>2</MaxCount>
    <MinDelay>5</MinDelay>
    <MaxDelay>10</MaxDelay>
    <DelayInSec>False</DelayInSec>
    <Duration>0</Duration>
    <DespawnTime>0</DespawnTime>
    <ProximityRange>-1</ProximityRange>
    <ProximityTriggerSound>500</ProximityTriggerSound>
    <TriggerProbability>1</TriggerProbability>
    <InContainer>False</InContainer>
    <MinRefractory>0</MinRefractory>
    <MaxRefractory>0</MaxRefractory>
    <TODStart>0</TODStart>
    <TODEnd>0</TODEnd>
    <TODMode>0</TODMode>
    <KillReset>1</KillReset>
    <ExternalTriggering>False</ExternalTriggering>
    <SequentialSpawning>-1</SequentialSpawning>
    <AllowGhostTriggering>False</AllowGhostTriggering>
    <AllowNPCTriggering>False</AllowNPCTriggering>
    <SpawnOnTrigger>False</SpawnOnTrigger>
    <SmartSpawning>False</SmartSpawning>
    <TickReset>False</TickReset>
    <Team>0</Team>
    <Amount>1</Amount>
    <IsGroup>False</IsGroup>
    <IsRunning>True</IsRunning>
    <IsHomeRangeRelative>True</IsHomeRangeRelative>
    <Objects2>ophidianwarrior:MX=2:SB=0:RT=0:TO=0:KL=0:RK=0:CA=1:DN=-1:DX=-1:SP=1:PR=-1</Objects2>
  </Points>
  <Points>
    <Name>tk</Name>
    <UniqueId>f8cec5ca-bd30-495b-a37e-921a4a96f0b6</UniqueId>
    <Map>Felucca</Map>
    <X>5247</X>
    <Y>1676</Y>
    <Width>40</Width>
    <Height>40</Height>
    <CentreX>5267</CentreX>
    <CentreY>1696</CentreY>
    <CentreZ>0</CentreZ>
    <Range>35</Range>
    <MaxCount>1</MaxCount>
    <MinDelay>5</MinDelay>
    <MaxDelay>10</MaxDelay>
    <DelayInSec>False</DelayInSec>
    <Duration>0</Duration>
    <DespawnTime>0</DespawnTime>
    <ProximityRange>-1</ProximityRange>
    <ProximityTriggerSound>500</ProximityTriggerSound>
    <TriggerProbability>1</TriggerProbability>
    <InContainer>False</InContainer>
    <MinRefractory>0</MinRefractory>
    <MaxRefractory>0</MaxRefractory>
    <TODStart>0</TODStart>
    <TODEnd>0</TODEnd>
    <TODMode>0</TODMode>
    <KillReset>1</KillReset>
    <ExternalTriggering>False</ExternalTriggering>
    <SequentialSpawning>-1</SequentialSpawning>
    <AllowGhostTriggering>False</AllowGhostTriggering>
    <AllowNPCTriggering>False</AllowNPCTriggering>
    <SpawnOnTrigger>False</SpawnOnTrigger>
    <SmartSpawning>False</SmartSpawning>
    <TickReset>False</TickReset>
    <Team>0</Team>
    <Amount>1</Amount>
    <IsGroup>False</IsGroup>
    <IsRunning>True</IsRunning>
    <IsHomeRangeRelative>True</IsHomeRangeRelative>
    <Objects2>ophidianmatriarch:MX=1:SB=0:RT=0:TO=0:KL=0:RK=0:CA=1:DN=-1:DX=-1:SP=1:PR=-1</Objects2>
  </Points>
  <Points>
    <Name>tk</Name>
    <UniqueId>fb62bc27-da04-4e52-a3ab-35b0d00dfdc0</UniqueId>
    <Map>Felucca</Map>
    <X>5343</X>
    <Y>1715</Y>
    <Width>10</Width>
    <Height>10</Height>
    <CentreX>5348</CentreX>
    <CentreY>1720</CentreY>
    <CentreZ>-92</CentreZ>
    <Range>5</Range>
    <MaxCount>1</MaxCount>
    <MinDelay>5</MinDelay>
    <MaxDelay>10</MaxDelay>
    <DelayInSec>False</DelayInSec>
    <Duration>0</Duration>
    <DespawnTime>0</DespawnTime>
    <ProximityRange>-1</ProximityRange>
    <ProximityTriggerSound>500</ProximityTriggerSound>
    <TriggerProbability>1</TriggerProbability>
    <InContainer>False</InContainer>
    <MinRefractory>0</MinRefractory>
    <MaxRefractory>0</MaxRefractory>
    <TODStart>0</TODStart>
    <TODEnd>0</TODEnd>
    <TODMode>0</TODMode>
    <KillReset>1</KillReset>
    <ExternalTriggering>False</ExternalTriggering>
    <SequentialSpawning>-1</SequentialSpawning>
    <AllowGhostTriggering>False</AllowGhostTriggering>
    <AllowNPCTriggering>False</AllowNPCTriggering>
    <SpawnOnTrigger>False</SpawnOnTrigger>
    <SmartSpawning>False</SmartSpawning>
    <TickReset>False</TickReset>
    <Team>0</Team>
    <Amount>1</Amount>
    <IsGroup>False</IsGroup>
    <IsRunning>True</IsRunning>
    <IsHomeRangeRelative>True</IsHomeRangeRelative>
    <Objects2>ophidianmage:MX=1:SB=0:RT=0:TO=0:KL=0:RK=0:CA=1:DN=-1:DX=-1:SP=1:PR=-1</Objects2>
  </Points>
  <Points>
    <Name>tk</Name>
    <UniqueId>fc22ccdf-f325-4f33-8374-3926b841178d</UniqueId>
    <Map>Felucca</Map>
    <X>5353</X>
    <Y>1543</Y>
    <Width>10</Width>
    <Height>10</Height>
    <CentreX>5358</CentreX>
    <CentreY>1548</CentreY>
    <CentreZ>0</CentreZ>
    <Range>5</Range>
    <MaxCount>3</MaxCount>
    <MinDelay>10</MinDelay>
    <MaxDelay>60</MaxDelay>
    <DelayInSec>True</DelayInSec>
    <Duration>0</Duration>
    <DespawnTime>0</DespawnTime>
    <ProximityRange>-1</ProximityRange>
    <ProximityTriggerSound>500</ProximityTriggerSound>
    <TriggerProbability>1</TriggerProbability>
    <InContainer>False</InContainer>
    <MinRefractory>0</MinRefractory>
    <MaxRefractory>0</MaxRefractory>
    <TODStart>0</TODStart>
    <TODEnd>0</TODEnd>
    <TODMode>0</TODMode>
    <KillReset>1</KillReset>
    <ExternalTriggering>False</ExternalTriggering>
    <SequentialSpawning>-1</SequentialSpawning>
    <AllowGhostTriggering>False</AllowGhostTriggering>
    <AllowNPCTriggering>False</AllowNPCTriggering>
    <SpawnOnTrigger>False</SpawnOnTrigger>
    <SmartSpawning>False</SmartSpawning>
    <TickReset>False</TickReset>
    <Team>0</Team>
    <Amount>1</Amount>
    <IsGroup>False</IsGroup>
    <IsRunning>True</IsRunning>
    <IsHomeRangeRelative>True</IsHomeRangeRelative>
    <Objects2>ophidianknight:MX=3:SB=0:RT=0:TO=0:KL=0:RK=0:CA=1:DN=-1:DX=-1:SP=1:PR=-1</Objects2>
  </Points>
</Spawns>